[{"heart_rate":55.0,"heart_rate_max":57.0,"heart_rate_min":53.0,"start_time":1613527200000,"end_time":1613527259000},{"heart_rate":56.0,"heart_rate_max":58.0,"heart_rate_min":54.0,"start_time":1613527260000,"end_time":1613527319000},{"heart_rate":57.0,"heart_rate_max":71.0,"heart_rate_min":54.0,"start_time":1613527320000,"end_time":1613527379000},{"heart_rate":55.0,"heart_rate_max":69.0,"heart_rate_min":53.0,"start_time":1613527380000,"end_time":1613527439000},{"heart_rate":53.0,"heart_rate_max":56.0,"heart_rate_min":51.0,"start_time":1613527440000,"end_time":1613527499000},{"heart_rate":53.0,"heart_rate_max":56.0,"heart_rate_min":51.0,"start_time":1613527500000,"end_time":1613527559000},{"heart_rate":54.0,"heart_rate_max":55.0,"heart_rate_min":53.0,"start_time":1613527560000,"end_time":1613527619000},{"heart_rate":55.0,"heart_rate_max":57.0,"heart_rate_min":54.0,"start_time":1613527620000,"end_time":1613527679000},{"heart_rate":54.0,"heart_rate_max":57.0,"heart_rate_min":52.0,"start_time":1613527680000,"end_time":1613527739000},{"heart_rate":54.0,"heart_rate_max":55.0,"heart_rate_min":54.0,"start_time":1613527740000,"end_time":1613527799000},{"heart_rate":55.0,"heart_rate_max":57.0,"heart_rate_min":54.0,"start_time":1613527800000,"end_time":1613527859000},{"heart_rate":54.0,"heart_rate_max":56.0,"heart_rate_min":54.0,"start_time":1613527860000,"end_time":1613527919000},{"heart_rate":55.0,"heart_rate_max":57.0,"heart_rate_min":54.0,"start_time":1613527920000,"end_time":1613527979000},{"heart_rate":55.0,"heart_rate_max":57.0,"heart_rate_min":55.0,"start_time":1613527980000,"end_time":1613528039000},{"heart_rate":55.0,"heart_rate_max":57.0,"heart_rate_min":54.0,"start_time":1613528040000,"end_time":1613528099000},{"heart_rate":56.0,"heart_rate_max":57.0,"heart_rate_min":55.0,"start_time":1613528100000,"end_time":1613528159000},{"heart_rate":55.0,"heart_rate_max":57.0,"heart_rate_min":54.0,"start_time":1613528160000,"end_time":1613528219000},{"heart_rate":55.0,"heart_rate_max":57.0,"heart_rate_min":52.0,"start_time":1613528220000,"end_time":1613528279000},{"heart_rate":55.0,"heart_rate_max":57.0,"heart_rate_min":55.0,"start_time":1613528280000,"end_time":1613528339000},{"heart_rate":55.0,"heart_rate_max":57.0,"heart_rate_min":53.0,"start_time":1613528340000,"end_time":1613528399000},{"heart_rate":56.0,"heart_rate_max":58.0,"heart_rate_min":54.0,"start_time":1613528400000,"end_time":1613528459000},{"heart_rate":54.0,"heart_rate_max":56.0,"heart_rate_min":53.0,"start_time":1613528460000,"end_time":1613528519000},{"heart_rate":54.0,"heart_rate_max":56.0,"heart_rate_min":53.0,"start_time":1613528520000,"end_time":1613528579000},{"heart_rate":54.0,"heart_rate_max":57.0,"heart_rate_min":53.0,"start_time":1613528580000,"end_time":1613528639000},{"heart_rate":55.0,"heart_rate_max":57.0,"heart_rate_min":54.0,"start_time":1613528640000,"end_time":1613528699000},{"heart_rate":54.0,"heart_rate_max":56.0,"heart_rate_min":54.0,"start_time":1613528700000,"end_time":1613528759000},{"heart_rate":56.0,"heart_rate_max":59.0,"heart_rate_min":54.0,"start_time":1613528760000,"end_time":1613528819000},{"heart_rate":55.0,"heart_rate_max":57.0,"heart_rate_min":53.0,"start_time":1613528820000,"end_time":1613528879000},{"heart_rate":55.0,"heart_rate_max":57.0,"heart_rate_min":54.0,"start_time":1613528880000,"end_time":1613528939000},{"heart_rate":54.0,"heart_rate_max":55.0,"heart_rate_min":54.0,"start_time":1613528940000,"end_time":1613528999000},{"heart_rate":55.0,"heart_rate_max":57.0,"heart_rate_min":54.0,"start_time":1613529000000,"end_time":1613529059000},{"heart_rate":55.0,"heart_rate_max":57.0,"heart_rate_min":54.0,"start_time":1613529060000,"end_time":1613529119000},{"heart_rate":55.0,"heart_rate_max":56.0,"heart_rate_min":54.0,"start_time":1613529120000,"end_time":1613529179000},{"heart_rate":55.0,"heart_rate_max":57.0,"heart_rate_min":55.0,"start_time":1613529180000,"end_time":1613529239000},{"heart_rate":56.0,"heart_rate_max":58.0,"heart_rate_min":55.0,"start_time":1613529240000,"end_time":1613529299000},{"heart_rate":55.0,"heart_rate_max":57.0,"heart_rate_min":55.0,"start_time":1613529300000,"end_time":1613529359000},{"heart_rate":54.0,"heart_rate_max":56.0,"heart_rate_min":54.0,"start_time":1613529360000,"end_time":1613529419000},{"heart_rate":55.0,"heart_rate_max":56.0,"heart_rate_min":55.0,"start_time":1613529420000,"end_time":1613529479000},{"heart_rate":54.0,"heart_rate_max":61.0,"heart_rate_min":51.0,"start_time":1613529480000,"end_time":1613529539000},{"heart_rate":59.0,"heart_rate_max":65.0,"heart_rate_min":54.0,"start_time":1613529540000,"end_time":1613529599000},{"heart_rate":52.0,"heart_rate_max":58.0,"heart_rate_min":51.0,"start_time":1613529600000,"end_time":1613529659000},{"heart_rate":53.0,"heart_rate_max":57.0,"heart_rate_min":51.0,"start_time":1613529660000,"end_time":1613529719000},{"heart_rate":54.0,"heart_rate_max":61.0,"heart_rate_min":51.0,"start_time":1613529720000,"end_time":1613529779000},{"heart_rate":52.0,"heart_rate_max":55.0,"heart_rate_min":50.0,"start_time":1613529780000,"end_time":1613529839000},{"heart_rate":53.0,"heart_rate_max":58.0,"heart_rate_min":51.0,"start_time":1613529840000,"end_time":1613529899000},{"heart_rate":52.0,"heart_rate_max":54.0,"heart_rate_min":51.0,"start_time":1613529900000,"end_time":1613529959000},{"heart_rate":53.0,"heart_rate_max":55.0,"heart_rate_min":52.0,"start_time":1613529960000,"end_time":1613530019000},{"heart_rate":52.0,"heart_rate_max":54.0,"heart_rate_min":51.0,"start_time":1613530020000,"end_time":1613530079000},{"heart_rate":53.0,"heart_rate_max":57.0,"heart_rate_min":50.0,"start_time":1613530080000,"end_time":1613530139000},{"heart_rate":52.0,"heart_rate_max":54.0,"heart_rate_min":51.0,"start_time":1613530140000,"end_time":1613530199000},{"heart_rate":53.0,"heart_rate_max":56.0,"heart_rate_min":51.0,"start_time":1613530200000,"end_time":1613530259000},{"heart_rate":54.0,"heart_rate_max":58.0,"heart_rate_min":52.0,"start_time":1613530260000,"end_time":1613530319000},{"heart_rate":51.0,"heart_rate_max":55.0,"heart_rate_min":48.0,"start_time":1613530320000,"end_time":1613530379000},{"heart_rate":52.0,"heart_rate_max":54.0,"heart_rate_min":50.0,"start_time":1613530380000,"end_time":1613530439000},{"heart_rate":53.0,"heart_rate_max":56.0,"heart_rate_min":51.0,"start_time":1613530440000,"end_time":1613530499000},{"heart_rate":53.0,"heart_rate_max":55.0,"heart_rate_min":51.0,"start_time":1613530500000,"end_time":1613530559000},{"heart_rate":55.0,"heart_rate_max":58.0,"heart_rate_min":53.0,"start_time":1613530560000,"end_time":1613530619000},{"heart_rate":53.0,"heart_rate_max":54.0,"heart_rate_min":52.0,"start_time":1613530620000,"end_time":1613530679000},{"heart_rate":56.0,"heart_rate_max":70.0,"heart_rate_min":52.0,"start_time":1613530680000,"end_time":1613530739000},{"heart_rate":58.0,"heart_rate_max":75.0,"heart_rate_min":52.0,"start_time":1613530740000,"end_time":1613530799000}]