[{"heart_rate":70.0,"heart_rate_max":77.0,"heart_rate_min":66.0,"start_time":1613660400000,"end_time":1613660459000},{"heart_rate":73.0,"heart_rate_max":78.0,"heart_rate_min":67.0,"start_time":1613660460000,"end_time":1613660519000},{"heart_rate":77.0,"heart_rate_max":86.0,"heart_rate_min":70.0,"start_time":1613660520000,"end_time":1613660579000},{"heart_rate":74.0,"heart_rate_max":77.0,"heart_rate_min":68.0,"start_time":1613660580000,"end_time":1613660639000},{"heart_rate":68.0,"heart_rate_max":71.0,"heart_rate_min":64.0,"start_time":1613660640000,"end_time":1613660699000},{"heart_rate":72.0,"heart_rate_max":77.0,"heart_rate_min":68.0,"start_time":1613660700000,"end_time":1613660759000},{"heart_rate":69.0,"heart_rate_max":72.0,"heart_rate_min":67.0,"start_time":1613660760000,"end_time":1613660819000},{"heart_rate":72.0,"heart_rate_max":76.0,"heart_rate_min":68.0,"start_time":1613660820000,"end_time":1613660879000},{"heart_rate":69.0,"heart_rate_max":72.0,"heart_rate_min":65.0,"start_time":1613660880000,"end_time":1613660939000},{"heart_rate":70.0,"heart_rate_max":72.0,"heart_rate_min":69.0,"start_time":1613660940000,"end_time":1613660999000},{"heart_rate":69.0,"heart_rate_max":73.0,"heart_rate_min":68.0,"start_time":1613661000000,"end_time":1613661059000},{"heart_rate":76.0,"heart_rate_max":79.0,"heart_rate_min":70.0,"start_time":1613661060000,"end_time":1613661119000},{"heart_rate":72.0,"heart_rate_max":75.0,"heart_rate_min":68.0,"start_time":1613661120000,"end_time":1613661179000},{"heart_rate":69.0,"heart_rate_max":73.0,"heart_rate_min":67.0,"start_time":1613661180000,"end_time":1613661239000},{"heart_rate":72.0,"heart_rate_max":81.0,"heart_rate_min":68.0,"start_time":1613661240000,"end_time":1613661299000},{"heart_rate":80.0,"heart_rate_max":84.0,"heart_rate_min":77.0,"start_time":1613661300000,"end_time":1613661359000},{"heart_rate":77.0,"heart_rate_max":84.0,"heart_rate_min":70.0,"start_time":1613661420000,"end_time":1613661479000},{"heart_rate":73.0,"heart_rate_max":76.0,"heart_rate_min":72.0,"start_time":1613661480000,"end_time":1613661539000},{"heart_rate":69.0,"heart_rate_max":73.0,"heart_rate_min":66.0,"start_time":1613661540000,"end_time":1613661599000},{"heart_rate":66.0,"heart_rate_max":69.0,"heart_rate_min":65.0,"start_time":1613661600000,"end_time":1613661659000},{"heart_rate":72.0,"heart_rate_max":77.0,"heart_rate_min":66.0,"start_time":1613661660000,"end_time":1613661719000},{"heart_rate":67.0,"heart_rate_max":69.0,"heart_rate_min":66.0,"start_time":1613661720000,"end_time":1613661779000},{"heart_rate":69.0,"heart_rate_max":70.0,"heart_rate_min":68.0,"start_time":1613661780000,"end_time":1613661839000},{"heart_rate":68.0,"heart_rate_max":71.0,"heart_rate_min":66.0,"start_time":1613661840000,"end_time":1613661899000},{"heart_rate":69.0,"heart_rate_max":73.0,"heart_rate_min":68.0,"start_time":1613661900000,"end_time":1613661959000},{"heart_rate":70.0,"heart_rate_max":72.0,"heart_rate_min":69.0,"start_time":1613661960000,"end_time":1613662019000},{"heart_rate":70.0,"heart_rate_max":72.0,"heart_rate_min":70.0,"start_time":1613662020000,"end_time":1613662079000},{"heart_rate":71.0,"heart_rate_max":73.0,"heart_rate_min":70.0,"start_time":1613662080000,"end_time":1613662139000},{"heart_rate":71.0,"heart_rate_max":73.0,"heart_rate_min":70.0,"start_time":1613662140000,"end_time":1613662199000},{"heart_rate":70.0,"heart_rate_max":74.0,"heart_rate_min":68.0,"start_time":1613662200000,"end_time":1613662259000},{"heart_rate":70.0,"heart_rate_max":73.0,"heart_rate_min":69.0,"start_time":1613662260000,"end_time":1613662319000},{"heart_rate":69.0,"heart_rate_max":73.0,"heart_rate_min":67.0,"start_time":1613662320000,"end_time":1613662379000},{"heart_rate":69.0,"heart_rate_max":73.0,"heart_rate_min":67.0,"start_time":1613662380000,"end_time":1613662439000},{"heart_rate":66.0,"heart_rate_max":74.0,"heart_rate_min":63.0,"start_time":1613662440000,"end_time":1613662499000},{"heart_rate":75.0,"heart_rate_max":82.0,"heart_rate_min":70.0,"start_time":1613662500000,"end_time":1613662559000},{"heart_rate":80.0,"heart_rate_max":84.0,"heart_rate_min":76.0,"start_time":1613662560000,"end_time":1613662619000},{"heart_rate":74.0,"heart_rate_max":75.0,"heart_rate_min":74.0,"start_time":1613662800000,"end_time":1613662859000},{"heart_rate":76.0,"heart_rate_max":77.0,"heart_rate_min":76.0,"start_time":1613662980000,"end_time":1613663039000},{"heart_rate":82.0,"heart_rate_max":83.0,"heart_rate_min":82.0,"start_time":1613663160000,"end_time":1613663219000},{"heart_rate":80.0,"heart_rate_max":84.0,"heart_rate_min":75.0,"start_time":1613663400000,"end_time":1613663459000},{"heart_rate":81.0,"heart_rate_max":86.0,"heart_rate_min":77.0,"start_time":1613663460000,"end_time":1613663519000},{"heart_rate":83.0,"heart_rate_max":91.0,"heart_rate_min":75.0,"start_time":1613663520000,"end_time":1613663579000},{"heart_rate":84.0,"heart_rate_max":87.0,"heart_rate_min":81.0,"start_time":1613663580000,"end_time":1613663639000},{"heart_rate":79.0,"heart_rate_max":85.0,"heart_rate_min":76.0,"start_time":1613663640000,"end_time":1613663699000},{"heart_rate":75.0,"heart_rate_max":77.0,"heart_rate_min":72.0,"start_time":1613663700000,"end_time":1613663759000},{"heart_rate":77.0,"heart_rate_max":81.0,"heart_rate_min":75.0,"start_time":1613663760000,"end_time":1613663819000},{"heart_rate":77.0,"heart_rate_max":82.0,"heart_rate_min":73.0,"start_time":1613663820000,"end_time":1613663879000},{"heart_rate":77.0,"heart_rate_max":86.0,"heart_rate_min":74.0,"start_time":1613663880000,"end_time":1613663939000}]