[{"heart_rate":66.0,"heart_rate_max":71.0,"heart_rate_min":61.0,"start_time":1612350000000,"end_time":1612350059000},{"heart_rate":64.0,"heart_rate_max":67.0,"heart_rate_min":61.0,"start_time":1612350060000,"end_time":1612350119000},{"heart_rate":69.0,"heart_rate_max":73.0,"heart_rate_min":65.0,"start_time":1612350120000,"end_time":1612350179000},{"heart_rate":65.0,"heart_rate_max":70.0,"heart_rate_min":62.0,"start_time":1612350180000,"end_time":1612350239000},{"heart_rate":65.0,"heart_rate_max":67.0,"heart_rate_min":61.0,"start_time":1612350240000,"end_time":1612350299000},{"heart_rate":70.0,"heart_rate_max":76.0,"heart_rate_min":65.0,"start_time":1612350300000,"end_time":1612350359000},{"heart_rate":66.0,"heart_rate_max":69.0,"heart_rate_min":64.0,"start_time":1612350360000,"end_time":1612350419000},{"heart_rate":68.0,"heart_rate_max":71.0,"heart_rate_min":66.0,"start_time":1612350420000,"end_time":1612350479000},{"heart_rate":66.0,"heart_rate_max":68.0,"heart_rate_min":64.0,"start_time":1612350480000,"end_time":1612350539000},{"heart_rate":65.0,"heart_rate_max":68.0,"heart_rate_min":64.0,"start_time":1612350540000,"end_time":1612350599000},{"heart_rate":66.0,"heart_rate_max":71.0,"heart_rate_min":64.0,"start_time":1612350600000,"end_time":1612350659000},{"heart_rate":74.0,"heart_rate_max":83.0,"heart_rate_min":71.0,"start_time":1612350660000,"end_time":1612350719000},{"heart_rate":70.0,"heart_rate_max":75.0,"heart_rate_min":65.0,"start_time":1612350720000,"end_time":1612350779000},{"heart_rate":66.0,"heart_rate_max":69.0,"heart_rate_min":64.0,"start_time":1612350780000,"end_time":1612350839000},{"heart_rate":67.0,"heart_rate_max":69.0,"heart_rate_min":66.0,"start_time":1612350840000,"end_time":1612350899000},{"heart_rate":65.0,"heart_rate_max":66.0,"heart_rate_min":64.0,"start_time":1612350900000,"end_time":1612350959000},{"heart_rate":71.0,"heart_rate_max":83.0,"heart_rate_min":64.0,"start_time":1612350960000,"end_time":1612351019000},{"heart_rate":79.0,"heart_rate_max":91.0,"heart_rate_min":68.0,"start_time":1612351020000,"end_time":1612351079000},{"heart_rate":97.0,"heart_rate_max":104.0,"heart_rate_min":91.0,"start_time":1612351080000,"end_time":1612351139000},{"heart_rate":83.0,"heart_rate_max":84.0,"heart_rate_min":82.0,"start_time":1612351140000,"end_time":1612351199000},{"heart_rate":81.0,"heart_rate_max":87.0,"heart_rate_min":78.0,"start_time":1612351200000,"end_time":1612351259000},{"heart_rate":73.0,"heart_rate_max":78.0,"heart_rate_min":68.0,"start_time":1612351260000,"end_time":1612351319000},{"heart_rate":69.0,"heart_rate_max":72.0,"heart_rate_min":67.0,"start_time":1612351320000,"end_time":1612351379000},{"heart_rate":70.0,"heart_rate_max":75.0,"heart_rate_min":66.0,"start_time":1612351380000,"end_time":1612351439000},{"heart_rate":82.0,"heart_rate_max":88.0,"heart_rate_min":72.0,"start_time":1612351440000,"end_time":1612351499000},{"heart_rate":81.0,"heart_rate_max":85.0,"heart_rate_min":79.0,"start_time":1612351500000,"end_time":1612351559000},{"heart_rate":79.0,"heart_rate_max":84.0,"heart_rate_min":75.0,"start_time":1612351560000,"end_time":1612351619000},{"heart_rate":79.0,"heart_rate_max":85.0,"heart_rate_min":74.0,"start_time":1612351620000,"end_time":1612351679000},{"heart_rate":79.0,"heart_rate_max":81.0,"heart_rate_min":77.0,"start_time":1612351680000,"end_time":1612351739000},{"heart_rate":77.0,"heart_rate_max":79.0,"heart_rate_min":77.0,"start_time":1612351740000,"end_time":1612351799000},{"heart_rate":74.0,"heart_rate_max":77.0,"heart_rate_min":72.0,"start_time":1612351980000,"end_time":1612352039000},{"heart_rate":79.0,"heart_rate_max":80.0,"heart_rate_min":78.0,"start_time":1612352040000,"end_time":1612352099000},{"heart_rate":67.0,"heart_rate_max":69.0,"heart_rate_min":64.0,"start_time":1612352340000,"end_time":1612352399000},{"heart_rate":70.0,"heart_rate_max":73.0,"heart_rate_min":64.0,"start_time":1612352400000,"end_time":1612352459000},{"heart_rate":73.0,"heart_rate_max":81.0,"heart_rate_min":69.0,"start_time":1612352460000,"end_time":1612352519000},{"heart_rate":73.0,"heart_rate_max":76.0,"heart_rate_min":71.0,"start_time":1612352520000,"end_time":1612352579000},{"heart_rate":71.0,"heart_rate_max":74.0,"heart_rate_min":68.0,"start_time":1612352580000,"end_time":1612352639000},{"heart_rate":67.0,"heart_rate_max":75.0,"heart_rate_min":62.0,"start_time":1612352640000,"end_time":1612352699000},{"heart_rate":71.0,"heart_rate_max":75.0,"heart_rate_min":68.0,"start_time":1612352700000,"end_time":1612352759000},{"heart_rate":71.0,"heart_rate_max":77.0,"heart_rate_min":62.0,"start_time":1612352760000,"end_time":1612352819000},{"heart_rate":71.0,"heart_rate_max":76.0,"heart_rate_min":67.0,"start_time":1612352820000,"end_time":1612352879000},{"heart_rate":70.0,"heart_rate_max":76.0,"heart_rate_min":68.0,"start_time":1612352880000,"end_time":1612352939000},{"heart_rate":73.0,"heart_rate_max":80.0,"heart_rate_min":68.0,"start_time":1612352940000,"end_time":1612352999000},{"heart_rate":75.0,"heart_rate_max":83.0,"heart_rate_min":69.0,"start_time":1612353000000,"end_time":1612353059000},{"heart_rate":78.0,"heart_rate_max":84.0,"heart_rate_min":73.0,"start_time":1612353060000,"end_time":1612353119000},{"heart_rate":82.0,"heart_rate_max":83.0,"heart_rate_min":81.0,"start_time":1612353120000,"end_time":1612353179000},{"heart_rate":81.0,"heart_rate_max":86.0,"heart_rate_min":77.0,"start_time":1612353180000,"end_time":1612353239000},{"heart_rate":73.0,"heart_rate_max":79.0,"heart_rate_min":70.0,"start_time":1612353240000,"end_time":1612353299000},{"heart_rate":75.0,"heart_rate_max":81.0,"heart_rate_min":69.0,"start_time":1612353300000,"end_time":1612353359000},{"heart_rate":81.0,"heart_rate_max":86.0,"heart_rate_min":75.0,"start_time":1612353360000,"end_time":1612353419000},{"heart_rate":79.0,"heart_rate_max":84.0,"heart_rate_min":75.0,"start_time":1612353420000,"end_time":1612353479000},{"heart_rate":78.0,"heart_rate_max":81.0,"heart_rate_min":72.0,"start_time":1612353480000,"end_time":1612353539000},{"heart_rate":69.0,"heart_rate_max":71.0,"heart_rate_min":69.0,"start_time":1612353540000,"end_time":1612353599000}]