[{"score":98,"score_max":100,"score_min":97,"flag":1,"level":1,"start_time":1608888060000,"end_time":1608888119999},{"score":100,"score_max":100,"score_min":100,"flag":1,"level":1,"start_time":1608888120000,"end_time":1608888179999},{"score":0,"score_max":2,"score_min":0,"flag":1,"level":0,"start_time":1608888180000,"end_time":1608888239999},{"score":10,"score_max":17,"score_min":2,"flag":1,"level":0,"start_time":1608888240000,"end_time":1608888299999},{"score":0,"score_max":1,"score_min":0,"flag":1,"level":0,"start_time":1608888360000,"end_time":1608888419999},{"score":0,"score_max":1,"score_min":0,"flag":1,"level":0,"start_time":1608888420000,"end_time":1608888479999},{"score":69,"score_max":83,"score_min":60,"flag":1,"level":0,"start_time":1608888900000,"end_time":1608888959999},{"score":80,"score_max":95,"score_min":58,"flag":1,"level":1,"start_time":1608888960000,"end_time":1608889019999},{"score":84,"score_max":96,"score_min":59,"flag":1,"level":1,"start_time":1608889020000,"end_time":1608889079999},{"score":63,"score_max":85,"score_min":54,"flag":1,"level":0,"start_time":1608889080000,"end_time":1608889139999},{"score":94,"score_max":99,"score_min":86,"flag":1,"level":1,"start_time":1608889140000,"end_time":1608889199999},{"score":99,"score_max":100,"score_min":99,"flag":1,"level":1,"start_time":1608889200000,"end_time":1608889259999}]