[{"elapsed_time":0,"segment":0,"interval":1,"start_time":1612091487030},{"elapsed_time":2448,"segment":0,"interval":1,"start_time":1612091489478},{"elapsed_time":6298,"segment":0,"interval":1,"start_time":1612091493328},{"elapsed_time":10022,"segment":0,"interval":1,"start_time":1612091497052},{"elapsed_time":10349,"segment":0,"interval":1,"start_time":1612091497379},{"elapsed_time":20033,"segment":0,"interval":1,"start_time":1612091507063},{"elapsed_time":20335,"segment":0,"interval":1,"start_time":1612091507365},{"elapsed_time":29162,"segment":0,"interval":1,"start_time":1612091516192},{"elapsed_time":30068,"segment":0,"interval":1,"start_time":1612091517098},{"elapsed_time":30323,"segment":0,"interval":1,"start_time":1612091517353},{"elapsed_time":40069,"segment":0,"interval":1,"start_time":1612091527099},{"elapsed_time":40328,"segment":0,"interval":1,"start_time":1612091527358},{"elapsed_time":42898,"segment":0,"interval":1,"start_time":1612091529928},{"elapsed_time":50072,"segment":0,"interval":1,"start_time":1612091537102},{"elapsed_time":50324,"segment":0,"interval":1,"start_time":1612091537354},{"elapsed_time":53774,"segment":0,"interval":1,"start_time":1612091540804},{"elapsed_time":60097,"segment":0,"interval":1,"start_time":1612091547127},{"elapsed_time":61327,"segment":0,"interval":1,"start_time":1612091548357},{"elapsed_time":64804,"segment":0,"interval":1,"start_time":1612091551834},{"elapsed_time":70100,"segment":0,"interval":1,"start_time":1612091557130},{"elapsed_time":70324,"segment":0,"interval":1,"start_time":1612091557354},{"elapsed_time":75576,"segment":0,"interval":1,"start_time":1612091562606},{"elapsed_time":80104,"segment":0,"interval":1,"start_time":1612091567134},{"elapsed_time":80325,"segment":0,"interval":1,"start_time":1612091567355},{"elapsed_time":86316,"segment":0,"interval":1,"start_time":1612091573346},{"elapsed_time":90127,"segment":0,"interval":1,"start_time":1612091577157},{"elapsed_time":90325,"segment":0,"interval":1,"start_time":1612091577355},{"elapsed_time":99039,"segment":0,"interval":1,"start_time":1612091586069},{"elapsed_time":100129,"segment":0,"interval":1,"start_time":1612091587159},{"elapsed_time":100321,"segment":0,"interval":1,"start_time":1612091587351},{"elapsed_time":110132,"segment":0,"interval":1,"start_time":1612091597162},{"elapsed_time":110320,"segment":0,"interval":1,"start_time":1612091597350},{"elapsed_time":112694,"segment":0,"interval":1,"start_time":1612091599724},{"elapsed_time":120156,"segment":0,"interval":1,"start_time":1612091607186},{"elapsed_time":120320,"segment":0,"interval":1,"start_time":1612091607350},{"elapsed_time":124503,"segment":0,"interval":1,"start_time":1612091611533},{"elapsed_time":130158,"segment":0,"interval":1,"start_time":1612091617188},{"elapsed_time":130322,"segment":0,"interval":1,"start_time":1612091617352},{"elapsed_time":135664,"segment":0,"interval":1,"start_time":1612091622694},{"elapsed_time":140160,"segment":0,"interval":1,"start_time":1612091627190},{"elapsed_time":140320,"segment":0,"interval":1,"start_time":1612091627350},{"elapsed_time":147942,"segment":0,"interval":1,"start_time":1612091634972},{"elapsed_time":150185,"segment":0,"interval":1,"start_time":1612091637215},{"elapsed_time":150327,"segment":0,"interval":1,"start_time":1612091637357},{"elapsed_time":159057,"segment":0,"interval":1,"start_time":1612091646087},{"elapsed_time":160187,"segment":0,"interval":1,"start_time":1612091647217},{"elapsed_time":161328,"segment":0,"interval":1,"start_time":1612091648358},{"elapsed_time":170188,"segment":0,"interval":1,"start_time":1612091657218},{"elapsed_time":170322,"segment":0,"interval":1,"start_time":1612091657352},{"elapsed_time":171815,"segment":0,"interval":1,"start_time":1612091658845},{"elapsed_time":180215,"segment":0,"interval":1,"start_time":1612091667245},{"elapsed_time":180316,"segment":0,"interval":1,"start_time":1612091667346},{"elapsed_time":183798,"segment":0,"interval":1,"start_time":1612091670828},{"elapsed_time":190217,"segment":0,"interval":1,"start_time":1612091677247},{"elapsed_time":190323,"segment":0,"interval":1,"start_time":1612091677353},{"elapsed_time":196164,"segment":0,"interval":1,"start_time":1612091683194},{"elapsed_time":200219,"segment":0,"interval":1,"start_time":1612091687249},{"elapsed_time":200324,"segment":0,"interval":1,"start_time":1612091687354},{"elapsed_time":210245,"segment":0,"interval":1,"start_time":1612091697275},{"elapsed_time":210320,"segment":0,"interval":1,"start_time":1612091697350},{"elapsed_time":210658,"segment":0,"interval":1,"start_time":1612091697688},{"elapsed_time":211789,"segment":0,"interval":1,"start_time":1612091698819},{"elapsed_time":220248,"segment":0,"interval":1,"start_time":1612091707278},{"elapsed_time":220322,"segment":0,"interval":1,"start_time":1612091707352},{"elapsed_time":221893,"segment":0,"interval":1,"start_time":1612091708923},{"elapsed_time":230251,"segment":0,"interval":1,"start_time":1612091717281},{"elapsed_time":230318,"segment":0,"interval":1,"start_time":1612091717348},{"elapsed_time":232722,"segment":0,"interval":1,"start_time":1612091719752},{"elapsed_time":240317,"segment":0,"interval":1,"start_time":1612091727347},{"elapsed_time":242273,"segment":0,"interval":1,"start_time":1612091729303},{"elapsed_time":243473,"segment":0,"interval":1,"start_time":1612091730503},{"elapsed_time":250274,"segment":0,"interval":1,"start_time":1612091737304},{"elapsed_time":250320,"segment":0,"interval":1,"start_time":1612091737350},{"elapsed_time":253761,"segment":0,"interval":1,"start_time":1612091740791},{"elapsed_time":261316,"segment":0,"interval":1,"start_time":1612091748346},{"elapsed_time":262565,"segment":0,"interval":1,"start_time":1612091749595},{"elapsed_time":264278,"segment":0,"interval":1,"start_time":1612091751308},{"elapsed_time":270303,"segment":0,"interval":1,"start_time":1612091757333},{"elapsed_time":270324,"segment":0,"interval":1,"start_time":1612091757354},{"elapsed_time":270554,"segment":0,"interval":1,"start_time":1612091757584},{"elapsed_time":279392,"segment":0,"interval":1,"start_time":1612091766422},{"elapsed_time":280305,"segment":0,"interval":1,"start_time":1612091767335},{"elapsed_time":280325,"segment":0,"interval":1,"start_time":1612091767355},{"elapsed_time":288292,"segment":0,"interval":1,"start_time":1612091775322},{"elapsed_time":290306,"segment":0,"interval":1,"start_time":1612091777336},{"elapsed_time":290327,"segment":0,"interval":1,"start_time":1612091777357},{"elapsed_time":300323,"segment":0,"interval":1,"start_time":1612091787353},{"elapsed_time":300332,"segment":0,"interval":1,"start_time":1612091787362},{"elapsed_time":301385,"segment":0,"interval":1,"start_time":1612091788415},{"elapsed_time":310324,"segment":0,"interval":1,"start_time":1612091797354},{"elapsed_time":310335,"segment":0,"interval":1,"start_time":1612091797365},{"elapsed_time":318208,"segment":0,"interval":1,"start_time":1612091805238},{"elapsed_time":320319,"segment":0,"interval":1,"start_time":1612091807349},{"elapsed_time":320337,"segment":0,"interval":1,"start_time":1612091807367},{"elapsed_time":330327,"segment":0,"interval":1,"start_time":1612091817357},{"elapsed_time":330362,"segment":0,"interval":1,"start_time":1612091817392},{"elapsed_time":332725,"segment":0,"interval":1,"start_time":1612091819755},{"elapsed_time":340328,"segment":0,"interval":1,"start_time":1612091827358},{"elapsed_time":340366,"segment":0,"interval":1,"start_time":1612091827396},{"elapsed_time":349558,"segment":0,"interval":1,"start_time":1612091836588},{"elapsed_time":350334,"segment":0,"interval":1,"start_time":1612091837364},{"elapsed_time":350369,"segment":0,"interval":1,"start_time":1612091837399},{"elapsed_time":360391,"segment":0,"interval":1,"start_time":1612091847421},{"elapsed_time":361319,"segment":0,"interval":1,"start_time":1612091848349},{"elapsed_time":366468,"segment":0,"interval":1,"start_time":1612091853498},{"elapsed_time":370325,"segment":0,"interval":1,"start_time":1612091857355},{"elapsed_time":370393,"segment":0,"interval":1,"start_time":1612091857423},{"elapsed_time":380321,"segment":0,"interval":1,"start_time":1612091867351},{"elapsed_time":380394,"segment":0,"interval":1,"start_time":1612091867424},{"elapsed_time":383827,"segment":0,"interval":1,"start_time":1612091870857},{"elapsed_time":390325,"segment":0,"interval":1,"start_time":1612091877355},{"elapsed_time":390529,"segment":0,"interval":1,"start_time":1612091877559},{"elapsed_time":400323,"segment":0,"interval":1,"start_time":1612091887353},{"elapsed_time":400530,"segment":0,"interval":1,"start_time":1612091887560},{"elapsed_time":410323,"segment":0,"interval":1,"start_time":1612091897353},{"elapsed_time":420327,"segment":0,"interval":1,"start_time":1612091907357},{"elapsed_time":424455,"segment":0,"interval":1,"start_time":1612091911485},{"elapsed_time":430321,"segment":0,"interval":1,"start_time":1612091917351},{"elapsed_time":436361,"segment":0,"interval":1,"start_time":1612091923391},{"elapsed_time":439457,"segment":0,"interval":1,"start_time":1612091926487},{"elapsed_time":440330,"segment":0,"interval":1,"start_time":1612091927360},{"elapsed_time":440458,"segment":0,"interval":1,"start_time":1612091927488},{"elapsed_time":450334,"segment":0,"interval":1,"start_time":1612091937364},{"elapsed_time":450460,"segment":0,"interval":1,"start_time":1612091937490},{"elapsed_time":460487,"segment":0,"interval":1,"start_time":1612091947517},{"elapsed_time":461328,"segment":0,"interval":1,"start_time":1612091948358},{"elapsed_time":461661,"segment":0,"interval":1,"start_time":1612091948691},{"elapsed_time":464105,"segment":0,"interval":1,"start_time":1612091951135},{"elapsed_time":470315,"segment":0,"interval":1,"start_time":1612091957345},{"elapsed_time":470493,"segment":0,"interval":1,"start_time":1612091957523},{"elapsed_time":475102,"segment":0,"interval":1,"start_time":1612091962132},{"elapsed_time":480321,"segment":0,"interval":1,"start_time":1612091967351},{"elapsed_time":480494,"segment":0,"interval":1,"start_time":1612091967524},{"elapsed_time":487023,"segment":0,"interval":1,"start_time":1612091974053},{"elapsed_time":490315,"segment":0,"interval":1,"start_time":1612091977345},{"elapsed_time":500313,"segment":0,"interval":1,"start_time":1612091987343},{"elapsed_time":501294,"segment":0,"interval":1,"start_time":1612091988324},{"elapsed_time":510311,"segment":0,"interval":1,"start_time":1612091997341},{"elapsed_time":517060,"segment":0,"interval":1,"start_time":1612092004090},{"elapsed_time":520313,"segment":0,"interval":1,"start_time":1612092007343},{"elapsed_time":530321,"segment":0,"interval":1,"start_time":1612092017351},{"elapsed_time":533075,"segment":0,"interval":1,"start_time":1612092020105},{"elapsed_time":540323,"segment":0,"interval":1,"start_time":1612092027353},{"elapsed_time":550315,"segment":0,"interval":1,"start_time":1612092037345},{"elapsed_time":551313,"segment":0,"interval":1,"start_time":1612092038343},{"elapsed_time":555575,"segment":0,"interval":1,"start_time":1612092042605},{"elapsed_time":560578,"segment":0,"interval":1,"start_time":1612092047608},{"elapsed_time":561321,"segment":0,"interval":1,"start_time":1612092048351},{"elapsed_time":566908,"segment":0,"interval":1,"start_time":1612092053938},{"elapsed_time":570318,"segment":0,"interval":1,"start_time":1612092057348},{"elapsed_time":570580,"segment":0,"interval":1,"start_time":1612092057610},{"elapsed_time":580323,"segment":0,"interval":1,"start_time":1612092067353},{"elapsed_time":580335,"segment":0,"interval":1,"start_time":1612092067365},{"elapsed_time":583607,"segment":0,"interval":1,"start_time":1612092070637},{"elapsed_time":590317,"segment":0,"interval":1,"start_time":1612092077347},{"elapsed_time":593310,"segment":0,"interval":1,"start_time":1612092080340},{"elapsed_time":600327,"segment":0,"interval":1,"start_time":1612092087357},{"elapsed_time":605623,"segment":0,"interval":1,"start_time":1612092092653},{"elapsed_time":610330,"segment":0,"interval":1,"start_time":1612092097360},{"elapsed_time":618733,"segment":0,"interval":1,"start_time":1612092105763},{"elapsed_time":620326,"segment":0,"interval":1,"start_time":1612092107356},{"elapsed_time":630325,"segment":0,"interval":1,"start_time":1612092117355},{"elapsed_time":632932,"segment":0,"interval":1,"start_time":1612092119962},{"elapsed_time":640331,"segment":0,"interval":1,"start_time":1612092127361},{"elapsed_time":644071,"segment":0,"interval":1,"start_time":1612092131101},{"elapsed_time":650330,"segment":0,"interval":1,"start_time":1612092137360},{"elapsed_time":655062,"segment":0,"interval":1,"start_time":1612092142092},{"elapsed_time":661326,"segment":0,"interval":1,"start_time":1612092148356},{"elapsed_time":665494,"segment":0,"interval":1,"start_time":1612092152524},{"elapsed_time":670318,"segment":0,"interval":1,"start_time":1612092157348},{"elapsed_time":676475,"segment":0,"interval":1,"start_time":1612092163505},{"elapsed_time":679719,"segment":0,"interval":1,"start_time":1612092166749},{"elapsed_time":680330,"segment":0,"interval":1,"start_time":1612092167360},{"elapsed_time":687742,"segment":0,"interval":1,"start_time":1612092174772},{"elapsed_time":690322,"segment":0,"interval":1,"start_time":1612092177352},{"elapsed_time":698893,"segment":0,"interval":1,"start_time":1612092185923},{"elapsed_time":700319,"segment":0,"interval":1,"start_time":1612092187349},{"elapsed_time":709374,"segment":0,"interval":1,"start_time":1612092196404},{"elapsed_time":710327,"segment":0,"interval":1,"start_time":1612092197357},{"elapsed_time":720320,"segment":0,"interval":1,"start_time":1612092207350},{"elapsed_time":721253,"segment":0,"interval":1,"start_time":1612092208283},{"elapsed_time":730326,"segment":0,"interval":1,"start_time":1612092217356},{"elapsed_time":734108,"segment":0,"interval":1,"start_time":1612092221138},{"elapsed_time":740319,"segment":0,"interval":1,"start_time":1612092227349},{"elapsed_time":747373,"segment":0,"interval":1,"start_time":1612092234403},{"elapsed_time":750328,"segment":0,"interval":1,"start_time":1612092237358},{"elapsed_time":760757,"segment":0,"interval":1,"start_time":1612092247787},{"elapsed_time":761319,"segment":0,"interval":1,"start_time":1612092248349},{"elapsed_time":770324,"segment":0,"interval":1,"start_time":1612092257354},{"elapsed_time":773786,"segment":0,"interval":1,"start_time":1612092260816},{"elapsed_time":780319,"segment":0,"interval":1,"start_time":1612092267349},{"elapsed_time":786851,"segment":0,"interval":1,"start_time":1612092273881},{"elapsed_time":790325,"segment":0,"interval":1,"start_time":1612092277355},{"elapsed_time":800228,"segment":0,"interval":1,"start_time":1612092287258},{"elapsed_time":800322,"segment":0,"interval":1,"start_time":1612092287352},{"elapsed_time":810323,"segment":0,"interval":1,"start_time":1612092297353},{"elapsed_time":820321,"segment":0,"interval":1,"start_time":1612092307351},{"elapsed_time":830325,"segment":0,"interval":1,"start_time":1612092317355},{"elapsed_time":840326,"segment":0,"interval":1,"start_time":1612092327356},{"elapsed_time":851325,"segment":0,"interval":1,"start_time":1612092338355},{"elapsed_time":861315,"segment":0,"interval":1,"start_time":1612092348345},{"elapsed_time":863518,"segment":0,"interval":1,"start_time":1612092350548},{"elapsed_time":870325,"segment":0,"interval":1,"start_time":1612092357355},{"elapsed_time":880317,"segment":0,"interval":1,"start_time":1612092367347},{"elapsed_time":881396,"segment":0,"interval":1,"start_time":1612092368426},{"elapsed_time":890315,"segment":0,"interval":1,"start_time":1612092377345},{"elapsed_time":897403,"segment":0,"interval":1,"start_time":1612092384433},{"elapsed_time":900314,"segment":0,"interval":1,"start_time":1612092387344},{"elapsed_time":910310,"segment":0,"interval":1,"start_time":1612092397340},{"elapsed_time":913887,"segment":0,"interval":1,"start_time":1612092400917},{"elapsed_time":920320,"segment":0,"interval":1,"start_time":1612092407350},{"elapsed_time":928219,"segment":0,"interval":1,"start_time":1612092415249},{"elapsed_time":930320,"segment":0,"interval":1,"start_time":1612092417350},{"elapsed_time":940313,"segment":0,"interval":1,"start_time":1612092427343},{"elapsed_time":940819,"segment":0,"interval":1,"start_time":1612092427849},{"elapsed_time":945490,"segment":0,"interval":1,"start_time":1612092432520},{"elapsed_time":951314,"segment":0,"interval":1,"start_time":1612092438344},{"elapsed_time":953267,"segment":0,"interval":1,"start_time":1612092440297},{"elapsed_time":961323,"segment":0,"interval":1,"start_time":1612092448353},{"elapsed_time":965718,"segment":0,"interval":1,"start_time":1612092452748},{"elapsed_time":970323,"segment":0,"interval":1,"start_time":1612092457353},{"elapsed_time":978530,"segment":0,"interval":1,"start_time":1612092465560},{"elapsed_time":980326,"segment":0,"interval":1,"start_time":1612092467356},{"elapsed_time":990321,"segment":0,"interval":1,"start_time":1612092477351},{"elapsed_time":990817,"segment":0,"interval":1,"start_time":1612092477847},{"elapsed_time":1000312,"segment":0,"interval":1,"start_time":1612092487342},{"elapsed_time":1003946,"segment":0,"interval":1,"start_time":1612092490976},{"elapsed_time":1010313,"segment":0,"interval":1,"start_time":1612092497343},{"elapsed_time":1016158,"segment":0,"interval":1,"start_time":1612092503188},{"elapsed_time":1020320,"segment":0,"interval":1,"start_time":1612092507350},{"elapsed_time":1028900,"segment":0,"interval":1,"start_time":1612092515930},{"elapsed_time":1030321,"segment":0,"interval":1,"start_time":1612092517351},{"elapsed_time":1040318,"segment":0,"interval":1,"start_time":1612092527348},{"elapsed_time":1041913,"segment":0,"interval":1,"start_time":1612092528943},{"elapsed_time":1051311,"segment":0,"interval":1,"start_time":1612092538341},{"elapsed_time":1054036,"segment":0,"interval":1,"start_time":1612092541066},{"elapsed_time":1061311,"segment":0,"interval":1,"start_time":1612092548341},{"elapsed_time":1065176,"segment":0,"interval":1,"start_time":1612092552206},{"elapsed_time":1070319,"segment":0,"interval":1,"start_time":1612092557349},{"elapsed_time":1077168,"segment":0,"interval":1,"start_time":1612092564198},{"elapsed_time":1080316,"segment":0,"interval":1,"start_time":1612092567346},{"elapsed_time":1089938,"segment":0,"interval":1,"start_time":1612092576968},{"elapsed_time":1090326,"segment":0,"interval":1,"start_time":1612092577356},{"elapsed_time":1100313,"segment":0,"interval":1,"start_time":1612092587343},{"elapsed_time":1101945,"segment":0,"interval":1,"start_time":1612092588975},{"elapsed_time":1110327,"segment":0,"interval":1,"start_time":1612092597357},{"elapsed_time":1113003,"segment":0,"interval":1,"start_time":1612092600033},{"elapsed_time":1120330,"segment":0,"interval":1,"start_time":1612092607360},{"elapsed_time":1123492,"segment":0,"interval":1,"start_time":1612092610522},{"elapsed_time":1130321,"segment":0,"interval":1,"start_time":1612092617351},{"elapsed_time":1133828,"segment":0,"interval":1,"start_time":1612092620858},{"elapsed_time":1138818,"segment":0,"interval":1,"start_time":1612092625848},{"elapsed_time":1140319,"segment":0,"interval":1,"start_time":1612092627349},{"elapsed_time":1144533,"segment":0,"interval":1,"start_time":1612092631563},{"elapsed_time":1151320,"segment":0,"interval":1,"start_time":1612092638350},{"elapsed_time":1155176,"segment":0,"interval":1,"start_time":1612092642206},{"elapsed_time":1161329,"segment":0,"interval":1,"start_time":1612092648359},{"elapsed_time":1165234,"segment":0,"interval":1,"start_time":1612092652264},{"elapsed_time":1170321,"segment":0,"interval":1,"start_time":1612092657351},{"elapsed_time":1176236,"segment":0,"interval":1,"start_time":1612092663266},{"elapsed_time":1180317,"segment":0,"interval":1,"start_time":1612092667347},{"elapsed_time":1186669,"segment":0,"interval":1,"start_time":1612092673699},{"elapsed_time":1190322,"segment":0,"interval":1,"start_time":1612092677352},{"elapsed_time":1198130,"segment":0,"interval":1,"start_time":1612092685160},{"elapsed_time":1200327,"segment":0,"interval":1,"start_time":1612092687357},{"elapsed_time":1208377,"segment":0,"interval":1,"start_time":1612092695407},{"elapsed_time":1210318,"segment":0,"interval":1,"start_time":1612092697348},{"elapsed_time":1219473,"segment":0,"interval":1,"start_time":1612092706503},{"elapsed_time":1220325,"segment":0,"interval":1,"start_time":1612092707355},{"elapsed_time":1230315,"segment":0,"interval":1,"start_time":1612092717345},{"elapsed_time":1235499,"segment":0,"interval":1,"start_time":1612092722529},{"elapsed_time":1240325,"segment":0,"interval":1,"start_time":1612092727355},{"elapsed_time":1247054,"segment":0,"interval":1,"start_time":1612092734084},{"elapsed_time":1251331,"segment":0,"interval":1,"start_time":1612092738361},{"elapsed_time":1257236,"segment":0,"interval":1,"start_time":1612092744266},{"elapsed_time":1261346,"segment":0,"interval":1,"start_time":1612092748376},{"elapsed_time":1267017,"segment":0,"interval":1,"start_time":1612092754047},{"elapsed_time":1270324,"segment":0,"interval":1,"start_time":1612092757354},{"elapsed_time":1276804,"segment":0,"interval":1,"start_time":1612092763834},{"elapsed_time":1280325,"segment":0,"interval":1,"start_time":1612092767355},{"elapsed_time":1286561,"segment":0,"interval":1,"start_time":1612092773591},{"elapsed_time":1290331,"segment":0,"interval":1,"start_time":1612092777361},{"elapsed_time":1296298,"segment":0,"interval":1,"start_time":1612092783328},{"elapsed_time":1300328,"segment":0,"interval":1,"start_time":1612092787358},{"elapsed_time":1306261,"segment":0,"interval":1,"start_time":1612092793291},{"elapsed_time":1310320,"segment":0,"interval":1,"start_time":1612092797350},{"elapsed_time":1312618,"segment":0,"interval":1,"start_time":1612092799648},{"elapsed_time":1319673,"segment":0,"interval":1,"start_time":1612092806703},{"elapsed_time":1320319,"segment":0,"interval":1,"start_time":1612092807349},{"elapsed_time":1330324,"segment":0,"interval":1,"start_time":1612092817354},{"elapsed_time":1332360,"segment":0,"interval":1,"start_time":1612092819390},{"elapsed_time":1340321,"segment":0,"interval":1,"start_time":1612092827351},{"elapsed_time":1343418,"segment":0,"interval":1,"start_time":1612092830448},{"elapsed_time":1351320,"segment":0,"interval":1,"start_time":1612092838350},{"elapsed_time":1353444,"segment":0,"interval":1,"start_time":1612092840474},{"elapsed_time":1361318,"segment":0,"interval":1,"start_time":1612092848348},{"elapsed_time":1363675,"segment":0,"interval":1,"start_time":1612092850705},{"elapsed_time":1370319,"segment":0,"interval":1,"start_time":1612092857349},{"elapsed_time":1374196,"segment":0,"interval":1,"start_time":1612092861226},{"elapsed_time":1380319,"segment":0,"interval":1,"start_time":1612092867349},{"elapsed_time":1389508,"segment":0,"interval":1,"start_time":1612092876538},{"elapsed_time":1390315,"segment":0,"interval":1,"start_time":1612092877345},{"elapsed_time":1400321,"segment":0,"interval":1,"start_time":1612092887351},{"elapsed_time":1400640,"segment":0,"interval":1,"start_time":1612092887670},{"elapsed_time":1410250,"segment":0,"interval":1,"start_time":1612092897280},{"elapsed_time":1410325,"segment":0,"interval":1,"start_time":1612092897355},{"elapsed_time":1419430,"segment":0,"interval":1,"start_time":1612092906460},{"elapsed_time":1420320,"segment":0,"interval":1,"start_time":1612092907350},{"elapsed_time":1428475,"segment":0,"interval":1,"start_time":1612092915505},{"elapsed_time":1430316,"segment":0,"interval":1,"start_time":1612092917346},{"elapsed_time":1437788,"segment":0,"interval":1,"start_time":1612092924818},{"elapsed_time":1440323,"segment":0,"interval":1,"start_time":1612092927353},{"elapsed_time":1447752,"segment":0,"interval":1,"start_time":1612092934782},{"elapsed_time":1451331,"segment":0,"interval":1,"start_time":1612092938361},{"elapsed_time":1458238,"segment":0,"interval":1,"start_time":1612092945268},{"elapsed_time":1461318,"segment":0,"interval":1,"start_time":1612092948348},{"elapsed_time":1468313,"segment":0,"interval":1,"start_time":1612092955343},{"elapsed_time":1470320,"segment":0,"interval":1,"start_time":1612092957350},{"elapsed_time":1480052,"segment":0,"interval":1,"start_time":1612092967082},{"elapsed_time":1480319,"segment":0,"interval":1,"start_time":1612092967349},{"elapsed_time":1488278,"segment":0,"interval":1,"start_time":1612092975308},{"elapsed_time":1490319,"segment":0,"interval":1,"start_time":1612092977349},{"elapsed_time":1493714,"segment":0,"interval":1,"start_time":1612092980744},{"elapsed_time":1500319,"segment":0,"interval":1,"start_time":1612092987349},{"elapsed_time":1505866,"segment":0,"interval":1,"start_time":1612092992896},{"elapsed_time":1510322,"segment":0,"interval":1,"start_time":1612092997352},{"elapsed_time":1516708,"segment":0,"interval":1,"start_time":1612093003738},{"elapsed_time":1520319,"segment":0,"interval":1,"start_time":1612093007349},{"elapsed_time":1526968,"segment":0,"interval":1,"start_time":1612093013998},{"elapsed_time":1530318,"segment":0,"interval":1,"start_time":1612093017348},{"elapsed_time":1536099,"segment":0,"interval":1,"start_time":1612093023129},{"elapsed_time":1540319,"segment":0,"interval":1,"start_time":1612093027349},{"elapsed_time":1545124,"segment":0,"interval":1,"start_time":1612093032154},{"elapsed_time":1551326,"segment":0,"interval":1,"start_time":1612093038356},{"elapsed_time":1553748,"segment":0,"interval":1,"start_time":1612093040778},{"elapsed_time":1561330,"segment":0,"interval":1,"start_time":1612093048360},{"elapsed_time":1563774,"segment":0,"interval":1,"start_time":1612093050804},{"elapsed_time":1570322,"segment":0,"interval":1,"start_time":1612093057352},{"elapsed_time":1577037,"segment":0,"interval":1,"start_time":1612093064067},{"elapsed_time":1580320,"segment":0,"interval":1,"start_time":1612093067350},{"elapsed_time":1587466,"segment":0,"interval":1,"start_time":1612093074496},{"elapsed_time":1590326,"segment":0,"interval":1,"start_time":1612093077356},{"elapsed_time":1597201,"segment":0,"interval":1,"start_time":1612093084231},{"elapsed_time":1600324,"segment":0,"interval":1,"start_time":1612093087354},{"elapsed_time":1606177,"segment":0,"interval":1,"start_time":1612093093207},{"elapsed_time":1610327,"segment":0,"interval":1,"start_time":1612093097357},{"elapsed_time":1614345,"segment":0,"interval":1,"start_time":1612093101375},{"elapsed_time":1615326,"segment":0,"interval":1,"start_time":1612093102356},{"elapsed_time":1620318,"segment":0,"interval":1,"start_time":1612093107348},{"elapsed_time":1624779,"segment":0,"interval":1,"start_time":1612093111809},{"elapsed_time":1630320,"segment":0,"interval":1,"start_time":1612093117350},{"elapsed_time":1638580,"segment":0,"interval":1,"start_time":1612093125610},{"elapsed_time":1640325,"segment":0,"interval":1,"start_time":1612093127355},{"elapsed_time":1649839,"segment":0,"interval":1,"start_time":1612093136869},{"elapsed_time":1651327,"segment":0,"interval":1,"start_time":1612093138357},{"elapsed_time":1660851,"segment":0,"interval":1,"start_time":1612093147881},{"elapsed_time":1661313,"segment":0,"interval":1,"start_time":1612093148343},{"elapsed_time":1664059,"segment":0,"interval":1,"start_time":1612093151089},{"elapsed_time":1670323,"segment":0,"interval":1,"start_time":1612093157353},{"elapsed_time":1675319,"segment":0,"interval":1,"start_time":1612093162349},{"elapsed_time":1680319,"segment":0,"interval":1,"start_time":1612093167349},{"elapsed_time":1686695,"segment":0,"interval":1,"start_time":1612093173725},{"elapsed_time":1690319,"segment":0,"interval":1,"start_time":1612093177349},{"elapsed_time":1700323,"segment":0,"interval":1,"start_time":1612093187353},{"elapsed_time":1702824,"segment":0,"interval":1,"start_time":1612093189854},{"elapsed_time":1710320,"segment":0,"interval":1,"start_time":1612093197350},{"elapsed_time":1713864,"segment":0,"interval":1,"start_time":1612093200894},{"elapsed_time":1720313,"segment":0,"interval":1,"start_time":1612093207343},{"elapsed_time":1728855,"segment":0,"interval":1,"start_time":1612093215885},{"elapsed_time":1730325,"segment":0,"interval":1,"start_time":1612093217355},{"elapsed_time":1739675,"segment":0,"interval":1,"start_time":1612093226705},{"elapsed_time":1740317,"segment":0,"interval":1,"start_time":1612093227347},{"elapsed_time":1751314,"segment":0,"interval":1,"start_time":1612093238344},{"elapsed_time":1751603,"segment":0,"interval":1,"start_time":1612093238633},{"elapsed_time":1761321,"segment":0,"interval":1,"start_time":1612093248351},{"elapsed_time":1761913,"segment":0,"interval":1,"start_time":1612093248943},{"elapsed_time":1770323,"segment":0,"interval":1,"start_time":1612093257353},{"elapsed_time":1771035,"segment":0,"interval":1,"start_time":1612093258065},{"elapsed_time":1780318,"segment":0,"interval":1,"start_time":1612093267348},{"elapsed_time":1785409,"segment":0,"interval":1,"start_time":1612093272439},{"elapsed_time":1790325,"segment":0,"interval":1,"start_time":1612093277355},{"elapsed_time":1800326,"segment":0,"interval":1,"start_time":1612093287356},{"elapsed_time":1810318,"segment":0,"interval":1,"start_time":1612093297348},{"elapsed_time":1820322,"segment":0,"interval":1,"start_time":1612093307352},{"elapsed_time":1830318,"segment":0,"interval":1,"start_time":1612093317348},{"elapsed_time":1840317,"segment":0,"interval":1,"start_time":1612093327347},{"elapsed_time":1851322,"segment":0,"interval":1,"start_time":1612093338352},{"elapsed_time":1851920,"segment":0,"interval":1,"start_time":1612093338950},{"elapsed_time":1861330,"segment":0,"interval":1,"start_time":1612093348360},{"elapsed_time":1870317,"segment":0,"interval":1,"start_time":1612093357347},{"elapsed_time":1874597,"segment":0,"interval":1,"start_time":1612093361627},{"elapsed_time":1880327,"segment":0,"interval":1,"start_time":1612093367357},{"elapsed_time":1890324,"segment":0,"interval":1,"start_time":1612093377354},{"elapsed_time":1893547,"segment":0,"interval":1,"start_time":1612093380577},{"elapsed_time":1900325,"segment":0,"interval":1,"start_time":1612093387355},{"elapsed_time":1900887,"segment":0,"interval":1,"start_time":1612093387917},{"elapsed_time":1908091,"segment":0,"interval":1,"start_time":1612093395121},{"elapsed_time":1910328,"segment":0,"interval":1,"start_time":1612093397358},{"elapsed_time":1910891,"segment":0,"interval":1,"start_time":1612093397921},{"elapsed_time":1920324,"segment":0,"interval":1,"start_time":1612093407354},{"elapsed_time":1920913,"segment":0,"interval":1,"start_time":1612093407943},{"elapsed_time":1921498,"segment":0,"interval":1,"start_time":1612093408528},{"elapsed_time":1930321,"segment":0,"interval":1,"start_time":1612093417351},{"elapsed_time":1930915,"segment":0,"interval":1,"start_time":1612093417945},{"elapsed_time":1931963,"segment":0,"interval":1,"start_time":1612093418993},{"elapsed_time":1933875,"segment":0,"interval":1,"start_time":1612093420905},{"elapsed_time":1940328,"segment":0,"interval":1,"start_time":1612093427358},{"elapsed_time":1940917,"segment":0,"interval":1,"start_time":1612093427947},{"elapsed_time":1949452,"segment":0,"interval":1,"start_time":1612093436482},{"elapsed_time":1950942,"segment":0,"interval":1,"start_time":1612093437972},{"elapsed_time":1951329,"segment":0,"interval":1,"start_time":1612093438359},{"elapsed_time":1960944,"segment":0,"interval":1,"start_time":1612093447974},{"elapsed_time":1961321,"segment":0,"interval":1,"start_time":1612093448351},{"elapsed_time":1965677,"segment":0,"interval":1,"start_time":1612093452707},{"elapsed_time":1970328,"segment":0,"interval":1,"start_time":1612093457358},{"elapsed_time":1970945,"segment":0,"interval":1,"start_time":1612093457975},{"elapsed_time":1980328,"segment":0,"interval":1,"start_time":1612093467358},{"elapsed_time":1980971,"segment":0,"interval":1,"start_time":1612093468001},{"elapsed_time":1981030,"segment":0,"interval":1,"start_time":1612093468060},{"elapsed_time":1990325,"segment":0,"interval":1,"start_time":1612093477355},{"elapsed_time":1990973,"segment":0,"interval":1,"start_time":1612093478003},{"elapsed_time":1992057,"segment":0,"interval":1,"start_time":1612093479087},{"elapsed_time":2000324,"segment":0,"interval":1,"start_time":1612093487354},{"elapsed_time":2000974,"segment":0,"interval":1,"start_time":1612093488004},{"elapsed_time":2001801,"segment":0,"interval":1,"start_time":1612093488831},{"elapsed_time":2010000,"segment":0,"interval":1,"start_time":1612093497030},{"elapsed_time":2010317,"segment":0,"interval":1,"start_time":1612093497347},{"elapsed_time":2012165,"segment":0,"interval":1,"start_time":1612093499195},{"elapsed_time":2020004,"segment":0,"interval":1,"start_time":1612093507034},{"elapsed_time":2020325,"segment":0,"interval":1,"start_time":1612093507355},{"elapsed_time":2025318,"segment":0,"interval":1,"start_time":1612093512348},{"elapsed_time":2030008,"segment":0,"interval":1,"start_time":1612093517038},{"elapsed_time":2030331,"segment":0,"interval":1,"start_time":1612093517361},{"elapsed_time":2039854,"segment":0,"interval":1,"start_time":1612093526884},{"elapsed_time":2040029,"segment":0,"interval":1,"start_time":1612093527059},{"elapsed_time":2040323,"segment":0,"interval":1,"start_time":1612093527353},{"elapsed_time":2051321,"segment":0,"interval":1,"start_time":1612093538351},{"elapsed_time":2061326,"segment":0,"interval":1,"start_time":1612093548356},{"elapsed_time":2070312,"segment":0,"interval":1,"start_time":1612093557342},{"elapsed_time":2075066,"segment":0,"interval":1,"start_time":1612093562096},{"elapsed_time":2080066,"segment":0,"interval":1,"start_time":1612093567096},{"elapsed_time":2080322,"segment":0,"interval":1,"start_time":1612093567352},{"elapsed_time":2087127,"segment":0,"interval":1,"start_time":1612093574157},{"elapsed_time":2090068,"segment":0,"interval":1,"start_time":1612093577098},{"elapsed_time":2090314,"segment":0,"interval":1,"start_time":1612093577344},{"elapsed_time":2097411,"segment":0,"interval":1,"start_time":1612093584441},{"elapsed_time":2100327,"segment":0,"interval":1,"start_time":1612093587357},{"elapsed_time":2104095,"segment":0,"interval":1,"start_time":1612093591125},{"elapsed_time":2106721,"segment":0,"interval":1,"start_time":1612093593751},{"elapsed_time":2110096,"segment":0,"interval":1,"start_time":1612093597126},{"elapsed_time":2110321,"segment":0,"interval":1,"start_time":1612093597351},{"elapsed_time":2115664,"segment":0,"interval":1,"start_time":1612093602694},{"elapsed_time":2120330,"segment":0,"interval":1,"start_time":1612093607360},{"elapsed_time":2124911,"segment":0,"interval":1,"start_time":1612093611941},{"elapsed_time":2130331,"segment":0,"interval":1,"start_time":1612093617361},{"elapsed_time":2134263,"segment":0,"interval":1,"start_time":1612093621293},{"elapsed_time":2140324,"segment":0,"interval":1,"start_time":1612093627354},{"elapsed_time":2143126,"segment":0,"interval":1,"start_time":1612093630156},{"elapsed_time":2143359,"segment":0,"interval":1,"start_time":1612093630389},{"elapsed_time":2151330,"segment":0,"interval":1,"start_time":1612093638360},{"elapsed_time":2151927,"segment":0,"interval":1,"start_time":1612093638957},{"elapsed_time":2152464,"segment":0,"interval":1,"start_time":1612093639494},{"elapsed_time":2161325,"segment":0,"interval":1,"start_time":1612093648355},{"elapsed_time":2161348,"segment":0,"interval":1,"start_time":1612093648378},{"elapsed_time":2170183,"segment":0,"interval":1,"start_time":1612093657213},{"elapsed_time":2170325,"segment":0,"interval":1,"start_time":1612093657355},{"elapsed_time":2178810,"segment":0,"interval":1,"start_time":1612093665840},{"elapsed_time":2180313,"segment":0,"interval":1,"start_time":1612093667343},{"elapsed_time":2187744,"segment":0,"interval":1,"start_time":1612093674774},{"elapsed_time":2190321,"segment":0,"interval":1,"start_time":1612093677351},{"elapsed_time":2198263,"segment":0,"interval":1,"start_time":1612093685293},{"elapsed_time":2200321,"segment":0,"interval":1,"start_time":1612093687351},{"elapsed_time":2209082,"segment":0,"interval":1,"start_time":1612093696112},{"elapsed_time":2210316,"segment":0,"interval":1,"start_time":1612093697346},{"elapsed_time":2219522,"segment":0,"interval":1,"start_time":1612093706552},{"elapsed_time":2220326,"segment":0,"interval":1,"start_time":1612093707356},{"elapsed_time":2230318,"segment":0,"interval":1,"start_time":1612093717348},{"elapsed_time":2230328,"segment":0,"interval":1,"start_time":1612093717358},{"elapsed_time":2240317,"segment":0,"interval":1,"start_time":1612093727347},{"elapsed_time":2242111,"segment":0,"interval":1,"start_time":1612093729141},{"elapsed_time":2251319,"segment":0,"interval":1,"start_time":1612093738349},{"elapsed_time":2253612,"segment":0,"interval":1,"start_time":1612093740642},{"elapsed_time":2261327,"segment":0,"interval":1,"start_time":1612093748357},{"elapsed_time":2265632,"segment":0,"interval":1,"start_time":1612093752662},{"elapsed_time":2270329,"segment":0,"interval":1,"start_time":1612093757359},{"elapsed_time":2280320,"segment":0,"interval":1,"start_time":1612093767350},{"elapsed_time":2280376,"segment":0,"interval":1,"start_time":1612093767406},{"elapsed_time":2290327,"segment":0,"interval":1,"start_time":1612093777357},{"elapsed_time":2297466,"segment":0,"interval":1,"start_time":1612093784496},{"elapsed_time":2300323,"segment":0,"interval":1,"start_time":1612093787353},{"elapsed_time":2310321,"segment":0,"interval":1,"start_time":1612093797351},{"elapsed_time":2311780,"segment":0,"interval":1,"start_time":1612093798810},{"elapsed_time":2320327,"segment":0,"interval":1,"start_time":1612093807357},{"elapsed_time":2327275,"segment":0,"interval":1,"start_time":1612093814305},{"elapsed_time":2330318,"segment":0,"interval":1,"start_time":1612093817348},{"elapsed_time":2340321,"segment":0,"interval":1,"start_time":1612093827351},{"elapsed_time":2343967,"segment":0,"interval":1,"start_time":1612093830997},{"elapsed_time":2344471,"segment":0,"interval":1,"start_time":1612093831501},{"elapsed_time":2351330,"segment":0,"interval":1,"start_time":1612093838360},{"elapsed_time":2359600,"segment":0,"interval":1,"start_time":1612093846630},{"elapsed_time":2361324,"segment":0,"interval":1,"start_time":1612093848354},{"elapsed_time":2370321,"segment":0,"interval":1,"start_time":1612093857351},{"elapsed_time":2374178,"segment":0,"interval":1,"start_time":1612093861208},{"elapsed_time":2380324,"segment":0,"interval":1,"start_time":1612093867354},{"elapsed_time":2386909,"segment":0,"interval":1,"start_time":1612093873939},{"elapsed_time":2390328,"segment":0,"interval":1,"start_time":1612093877358},{"elapsed_time":2400327,"segment":0,"interval":1,"start_time":1612093887357},{"elapsed_time":2400370,"segment":0,"interval":1,"start_time":1612093887400},{"elapsed_time":2410330,"segment":0,"interval":1,"start_time":1612093897360},{"elapsed_time":2412964,"segment":0,"interval":1,"start_time":1612093899994},{"elapsed_time":2420323,"segment":0,"interval":1,"start_time":1612093907353},{"elapsed_time":2425220,"segment":0,"interval":1,"start_time":1612093912250},{"elapsed_time":2430327,"segment":0,"interval":1,"start_time":1612093917357},{"elapsed_time":2437171,"segment":0,"interval":1,"start_time":1612093924201},{"elapsed_time":2440336,"segment":0,"interval":1,"start_time":1612093927366},{"elapsed_time":2449342,"segment":0,"interval":1,"start_time":1612093936372},{"elapsed_time":2451327,"segment":0,"interval":1,"start_time":1612093938357},{"elapsed_time":2461325,"segment":0,"interval":1,"start_time":1612093948355},{"elapsed_time":2463483,"segment":0,"interval":1,"start_time":1612093950513},{"elapsed_time":2470326,"segment":0,"interval":1,"start_time":1612093957356},{"elapsed_time":2479901,"segment":0,"interval":1,"start_time":1612093966931},{"elapsed_time":2480331,"segment":0,"interval":1,"start_time":1612093967361},{"elapsed_time":2490327,"segment":0,"interval":1,"start_time":1612093977357},{"elapsed_time":2495716,"segment":0,"interval":1,"start_time":1612093982746},{"elapsed_time":2500329,"segment":0,"interval":1,"start_time":1612093987359},{"elapsed_time":2510326,"segment":0,"interval":1,"start_time":1612093997356},{"elapsed_time":2510460,"segment":0,"interval":1,"start_time":1612093997490},{"elapsed_time":2520325,"segment":0,"interval":1,"start_time":1612094007355},{"elapsed_time":2523049,"segment":0,"interval":1,"start_time":1612094010079},{"elapsed_time":2530323,"segment":0,"interval":1,"start_time":1612094017353},{"elapsed_time":2534148,"segment":0,"interval":1,"start_time":1612094021178},{"elapsed_time":2536513,"segment":0,"interval":1,"start_time":1612094023543},{"elapsed_time":2540330,"segment":0,"interval":1,"start_time":1612094027360},{"elapsed_time":2540514,"segment":0,"interval":1,"start_time":1612094027544},{"elapsed_time":2544858,"segment":0,"interval":1,"start_time":1612094031888},{"elapsed_time":2550535,"segment":0,"interval":1,"start_time":1612094037565},{"elapsed_time":2551329,"segment":0,"interval":1,"start_time":1612094038359},{"elapsed_time":2555431,"segment":0,"interval":1,"start_time":1612094042461},{"elapsed_time":2556775,"segment":0,"interval":1,"start_time":1612094043805},{"elapsed_time":2560537,"segment":0,"interval":1,"start_time":1612094047567},{"elapsed_time":2561317,"segment":0,"interval":1,"start_time":1612094048347},{"elapsed_time":2565745,"segment":0,"interval":1,"start_time":1612094052775},{"elapsed_time":2570328,"segment":0,"interval":1,"start_time":1612094057358},{"elapsed_time":2570539,"segment":0,"interval":1,"start_time":1612094057569},{"elapsed_time":2575842,"segment":0,"interval":1,"start_time":1612094062872},{"elapsed_time":2580313,"segment":0,"interval":1,"start_time":1612094067343},{"elapsed_time":2580564,"segment":0,"interval":1,"start_time":1612094067594},{"elapsed_time":2585541,"segment":0,"interval":1,"start_time":1612094072571},{"elapsed_time":2590322,"segment":0,"interval":1,"start_time":1612094077352},{"elapsed_time":2590566,"segment":0,"interval":1,"start_time":1612094077596},{"elapsed_time":2595892,"segment":0,"interval":1,"start_time":1612094082922},{"elapsed_time":2600330,"segment":0,"interval":1,"start_time":1612094087360},{"elapsed_time":2600567,"segment":0,"interval":1,"start_time":1612094087597},{"elapsed_time":2607575,"segment":0,"interval":1,"start_time":1612094094605},{"elapsed_time":2610313,"segment":0,"interval":1,"start_time":1612094097343},{"elapsed_time":2610575,"segment":0,"interval":1,"start_time":1612094097605},{"elapsed_time":2619830,"segment":0,"interval":1,"start_time":1612094106860},{"elapsed_time":2620301,"segment":0,"interval":1,"start_time":1612094107331},{"elapsed_time":2620571,"segment":0,"interval":1,"start_time":1612094107601},{"elapsed_time":2630325,"segment":0,"interval":1,"start_time":1612094117355},{"elapsed_time":2630582,"segment":0,"interval":1,"start_time":1612094117612},{"elapsed_time":2632452,"segment":0,"interval":1,"start_time":1612094119482},{"elapsed_time":2640320,"segment":0,"interval":1,"start_time":1612094127350},{"elapsed_time":2640616,"segment":0,"interval":1,"start_time":1612094127646},{"elapsed_time":2645079,"segment":0,"interval":1,"start_time":1612094132109},{"elapsed_time":2650618,"segment":0,"interval":1,"start_time":1612094137648},{"elapsed_time":2651320,"segment":0,"interval":1,"start_time":1612094138350},{"elapsed_time":2657519,"segment":0,"interval":1,"start_time":1612094144549},{"elapsed_time":2660620,"segment":0,"interval":1,"start_time":1612094147650},{"elapsed_time":2661320,"segment":0,"interval":1,"start_time":1612094148350},{"elapsed_time":2670320,"segment":0,"interval":1,"start_time":1612094157350},{"elapsed_time":2670653,"segment":0,"interval":1,"start_time":1612094157683},{"elapsed_time":2670737,"segment":0,"interval":1,"start_time":1612094157767},{"elapsed_time":2680325,"segment":0,"interval":1,"start_time":1612094167355},{"elapsed_time":2680656,"segment":0,"interval":1,"start_time":1612094167686},{"elapsed_time":2684846,"segment":0,"interval":1,"start_time":1612094171876},{"elapsed_time":2690323,"segment":0,"interval":1,"start_time":1612094177353},{"elapsed_time":2690665,"segment":0,"interval":1,"start_time":1612094177695},{"elapsed_time":2700111,"segment":0,"interval":1,"start_time":1612094187141},{"elapsed_time":2700313,"segment":0,"interval":1,"start_time":1612094187343},{"elapsed_time":2700687,"segment":0,"interval":1,"start_time":1612094187717},{"elapsed_time":2710324,"segment":0,"interval":1,"start_time":1612094197354},{"elapsed_time":2710689,"segment":0,"interval":1,"start_time":1612094197719},{"elapsed_time":2715137,"segment":0,"interval":1,"start_time":1612094202167},{"elapsed_time":2720317,"segment":0,"interval":1,"start_time":1612094207347},{"elapsed_time":2720692,"segment":0,"interval":1,"start_time":1612094207722},{"elapsed_time":2729990,"segment":0,"interval":1,"start_time":1612094217020},{"elapsed_time":2730320,"segment":0,"interval":1,"start_time":1612094217350},{"elapsed_time":2730719,"segment":0,"interval":1,"start_time":1612094217749},{"elapsed_time":2740326,"segment":0,"interval":1,"start_time":1612094227356},{"elapsed_time":2747456,"segment":0,"interval":1,"start_time":1612094234486},{"elapsed_time":2751321,"segment":0,"interval":1,"start_time":1612094238351},{"elapsed_time":2760327,"segment":0,"interval":1,"start_time":1612094247357},{"elapsed_time":2765305,"segment":0,"interval":1,"start_time":1612094252335},{"elapsed_time":2769189,"segment":0,"interval":1,"start_time":1612094256219},{"elapsed_time":2770319,"segment":0,"interval":1,"start_time":1612094257349},{"elapsed_time":2780330,"segment":0,"interval":1,"start_time":1612094267360},{"elapsed_time":2782195,"segment":0,"interval":1,"start_time":1612094269225},{"elapsed_time":2790327,"segment":0,"interval":1,"start_time":1612094277357},{"elapsed_time":2799127,"segment":0,"interval":1,"start_time":1612094286157},{"elapsed_time":2800328,"segment":0,"interval":1,"start_time":1612094287358},{"elapsed_time":2810326,"segment":0,"interval":1,"start_time":1612094297356},{"elapsed_time":2820316,"segment":0,"interval":1,"start_time":1612094307346},{"elapsed_time":2830316,"segment":0,"interval":1,"start_time":1612094317346},{"elapsed_time":2840311,"segment":0,"interval":1,"start_time":1612094327341},{"elapsed_time":2851321,"segment":0,"interval":1,"start_time":1612094338351},{"elapsed_time":2860322,"segment":0,"interval":1,"start_time":1612094347352},{"elapsed_time":2863330,"segment":0,"interval":1,"start_time":1612094350360},{"elapsed_time":2870320,"segment":0,"interval":1,"start_time":1612094357350},{"elapsed_time":2870838,"segment":0,"interval":1,"start_time":1612094357868},{"elapsed_time":2880326,"segment":0,"interval":1,"start_time":1612094367356},{"elapsed_time":2880839,"segment":0,"interval":1,"start_time":1612094367869},{"elapsed_time":2881405,"segment":0,"interval":1,"start_time":1612094368435},{"elapsed_time":2890319,"segment":0,"interval":1,"start_time":1612094377349},{"elapsed_time":2890858,"segment":0,"interval":1,"start_time":1612094377888},{"elapsed_time":2899713,"segment":0,"interval":1,"start_time":1612094386743},{"elapsed_time":2900322,"segment":0,"interval":1,"start_time":1612094387352},{"elapsed_time":2900860,"segment":0,"interval":1,"start_time":1612094387890},{"elapsed_time":2910324,"segment":0,"interval":1,"start_time":1612094397354},{"elapsed_time":2910861,"segment":0,"interval":1,"start_time":1612094397891},{"elapsed_time":2920324,"segment":0,"interval":1,"start_time":1612094407354},{"elapsed_time":2920886,"segment":0,"interval":1,"start_time":1612094407916},{"elapsed_time":2930321,"segment":0,"interval":1,"start_time":1612094417351},{"elapsed_time":2930888,"segment":0,"interval":1,"start_time":1612094417918},{"elapsed_time":2940321,"segment":0,"interval":1,"start_time":1612094427351},{"elapsed_time":2940889,"segment":0,"interval":1,"start_time":1612094427919},{"elapsed_time":2950918,"segment":0,"interval":1,"start_time":1612094437948},{"elapsed_time":2951319,"segment":0,"interval":1,"start_time":1612094438349},{"elapsed_time":2960323,"segment":0,"interval":1,"start_time":1612094447353},{"elapsed_time":2968925,"segment":0,"interval":1,"start_time":1612094455955},{"elapsed_time":2969234,"segment":0,"interval":1,"start_time":1612094456264},{"elapsed_time":2970319,"segment":0,"interval":1,"start_time":1612094457349},{"elapsed_time":2970925,"segment":0,"interval":1,"start_time":1612094457955},{"elapsed_time":2980326,"segment":0,"interval":1,"start_time":1612094467356},{"elapsed_time":2980948,"segment":0,"interval":1,"start_time":1612094467978},{"elapsed_time":2983667,"segment":0,"interval":1,"start_time":1612094470697},{"elapsed_time":2990322,"segment":0,"interval":1,"start_time":1612094477352},{"elapsed_time":2990951,"segment":0,"interval":1,"start_time":1612094477981},{"elapsed_time":2999324,"segment":0,"interval":1,"start_time":1612094486354},{"elapsed_time":3000322,"segment":0,"interval":1,"start_time":1612094487352},{"elapsed_time":3000952,"segment":0,"interval":1,"start_time":1612094487982},{"elapsed_time":3010327,"segment":0,"interval":1,"start_time":1612094497357},{"elapsed_time":3010977,"segment":0,"interval":1,"start_time":1612094498007},{"elapsed_time":3016050,"segment":0,"interval":1,"start_time":1612094503080},{"elapsed_time":3020318,"segment":0,"interval":1,"start_time":1612094507348},{"elapsed_time":3020981,"segment":0,"interval":1,"start_time":1612094508011},{"elapsed_time":3030314,"segment":0,"interval":1,"start_time":1612094517344},{"elapsed_time":3030984,"segment":0,"interval":1,"start_time":1612094518014},{"elapsed_time":3032367,"segment":0,"interval":1,"start_time":1612094519397},{"elapsed_time":3040005,"segment":0,"interval":1,"start_time":1612094527035},{"elapsed_time":3040324,"segment":0,"interval":1,"start_time":1612094527354},{"elapsed_time":3048852,"segment":0,"interval":1,"start_time":1612094535882},{"elapsed_time":3050007,"segment":0,"interval":1,"start_time":1612094537037},{"elapsed_time":3051321,"segment":0,"interval":1,"start_time":1612094538351},{"elapsed_time":3060008,"segment":0,"interval":1,"start_time":1612094547038},{"elapsed_time":3060322,"segment":0,"interval":1,"start_time":1612094547352},{"elapsed_time":3065077,"segment":0,"interval":1,"start_time":1612094552107},{"elapsed_time":3070319,"segment":0,"interval":1,"start_time":1612094557349},{"elapsed_time":3071036,"segment":0,"interval":1,"start_time":1612094558066},{"elapsed_time":3080315,"segment":0,"interval":1,"start_time":1612094567345},{"elapsed_time":3081678,"segment":0,"interval":1,"start_time":1612094568708},{"elapsed_time":3090042,"segment":0,"interval":1,"start_time":1612094577072},{"elapsed_time":3090327,"segment":0,"interval":1,"start_time":1612094577357},{"elapsed_time":3100065,"segment":0,"interval":1,"start_time":1612094587095},{"elapsed_time":3100319,"segment":0,"interval":1,"start_time":1612094587349},{"elapsed_time":3105358,"segment":0,"interval":1,"start_time":1612094592388},{"elapsed_time":3110066,"segment":0,"interval":1,"start_time":1612094597096},{"elapsed_time":3110318,"segment":0,"interval":1,"start_time":1612094597348},{"elapsed_time":3120068,"segment":0,"interval":1,"start_time":1612094607098},{"elapsed_time":3120320,"segment":0,"interval":1,"start_time":1612094607350},{"elapsed_time":3130094,"segment":0,"interval":1,"start_time":1612094617124},{"elapsed_time":3130319,"segment":0,"interval":1,"start_time":1612094617349},{"elapsed_time":3130855,"segment":0,"interval":1,"start_time":1612094617885},{"elapsed_time":3140097,"segment":0,"interval":1,"start_time":1612094627127},{"elapsed_time":3140317,"segment":0,"interval":1,"start_time":1612094627347},{"elapsed_time":3149418,"segment":0,"interval":1,"start_time":1612094636448},{"elapsed_time":3151318,"segment":0,"interval":1,"start_time":1612094638348},{"elapsed_time":3154830,"segment":0,"interval":1,"start_time":1612094641860},{"elapsed_time":3160310,"segment":0,"interval":1,"start_time":1612094647340},{"elapsed_time":3166621,"segment":0,"interval":1,"start_time":1612094653651},{"elapsed_time":3170346,"segment":0,"interval":1,"start_time":1612094657376},{"elapsed_time":3180318,"segment":0,"interval":1,"start_time":1612094667348},{"elapsed_time":3183723,"segment":0,"interval":1,"start_time":1612094670753},{"elapsed_time":3190322,"segment":0,"interval":1,"start_time":1612094677352},{"elapsed_time":3199150,"segment":0,"interval":1,"start_time":1612094686180},{"elapsed_time":3200151,"segment":0,"interval":1,"start_time":1612094687181},{"elapsed_time":3200318,"segment":0,"interval":1,"start_time":1612094687348},{"elapsed_time":3210177,"segment":0,"interval":1,"start_time":1612094697207},{"elapsed_time":3210317,"segment":0,"interval":1,"start_time":1612094697347},{"elapsed_time":3216114,"segment":0,"interval":1,"start_time":1612094703144},{"elapsed_time":3220313,"segment":0,"interval":1,"start_time":1612094707343},{"elapsed_time":3230311,"segment":0,"interval":1,"start_time":1612094717341},{"elapsed_time":3233507,"segment":0,"interval":1,"start_time":1612094720537},{"elapsed_time":3240322,"segment":0,"interval":1,"start_time":1612094727352},{"elapsed_time":3241206,"segment":0,"interval":1,"start_time":1612094728236},{"elapsed_time":3251322,"segment":0,"interval":1,"start_time":1612094738352},{"elapsed_time":3260323,"segment":0,"interval":1,"start_time":1612094747353},{"elapsed_time":3270323,"segment":0,"interval":1,"start_time":1612094757353},{"elapsed_time":3280315,"segment":0,"interval":1,"start_time":1612094767345},{"elapsed_time":3294039,"segment":1,"interval":1,"start_time":1612095412259},{"elapsed_time":3304127,"segment":1,"interval":1,"start_time":1612095422347},{"elapsed_time":3310124,"segment":1,"interval":1,"start_time":1612095428344},{"elapsed_time":3320127,"segment":1,"interval":1,"start_time":1612095438347},{"elapsed_time":3320547,"segment":1,"interval":1,"start_time":1612095438767},{"elapsed_time":3334129,"segment":1,"interval":1,"start_time":1612095452349},{"elapsed_time":3344130,"segment":1,"interval":1,"start_time":1612095462350},{"elapsed_time":3346157,"segment":1,"interval":1,"start_time":1612095464377},{"elapsed_time":3354136,"segment":1,"interval":1,"start_time":1612095472356},{"elapsed_time":3364660,"segment":1,"interval":1,"start_time":1612095482880},{"elapsed_time":3365140,"segment":1,"interval":1,"start_time":1612095483360},{"elapsed_time":3375137,"segment":1,"interval":1,"start_time":1612095493357},{"elapsed_time":3384133,"segment":1,"interval":1,"start_time":1612095502353},{"elapsed_time":3385618,"segment":1,"interval":1,"start_time":1612095503838},{"elapsed_time":3394134,"segment":1,"interval":1,"start_time":1612095512354},{"elapsed_time":3404143,"segment":1,"interval":1,"start_time":1612095522363},{"elapsed_time":3407421,"segment":1,"interval":1,"start_time":1612095525641},{"elapsed_time":3410129,"segment":1,"interval":1,"start_time":1612095528349},{"elapsed_time":3420130,"segment":1,"interval":1,"start_time":1612095538350},{"elapsed_time":3434127,"segment":1,"interval":1,"start_time":1612095552347},{"elapsed_time":3434635,"segment":1,"interval":1,"start_time":1612095552855},{"elapsed_time":3444125,"segment":1,"interval":1,"start_time":1612095562345},{"elapsed_time":3454127,"segment":1,"interval":1,"start_time":1612095572347},{"elapsed_time":3458296,"segment":1,"interval":1,"start_time":1612095576516},{"elapsed_time":3465122,"segment":1,"interval":1,"start_time":1612095583342},{"elapsed_time":3475131,"segment":1,"interval":1,"start_time":1612095593351},{"elapsed_time":3480745,"segment":1,"interval":1,"start_time":1612095598965},{"elapsed_time":3484127,"segment":1,"interval":1,"start_time":1612095602347},{"elapsed_time":3494128,"segment":1,"interval":1,"start_time":1612095612348},{"elapsed_time":3504126,"segment":1,"interval":1,"start_time":1612095622346},{"elapsed_time":3510125,"segment":1,"interval":1,"start_time":1612095628345},{"elapsed_time":3519914,"segment":1,"interval":1,"start_time":1612095638134},{"elapsed_time":3520127,"segment":1,"interval":1,"start_time":1612095638347},{"elapsed_time":3534129,"segment":1,"interval":1,"start_time":1612095652349},{"elapsed_time":3539940,"segment":1,"interval":1,"start_time":1612095658160},{"elapsed_time":3544120,"segment":1,"interval":1,"start_time":1612095662340},{"elapsed_time":3554124,"segment":1,"interval":1,"start_time":1612095672344},{"elapsed_time":3557597,"segment":1,"interval":1,"start_time":1612095675817},{"elapsed_time":3565122,"segment":1,"interval":1,"start_time":1612095683342},{"elapsed_time":3565502,"segment":1,"interval":1,"start_time":1612095683722},{"elapsed_time":3575126,"segment":1,"interval":1,"start_time":1612095693346},{"elapsed_time":3581020,"segment":1,"interval":1,"start_time":1612095699240},{"elapsed_time":3584125,"segment":1,"interval":1,"start_time":1612095702345},{"elapsed_time":3594128,"segment":1,"interval":1,"start_time":1612095712348},{"elapsed_time":3604125,"segment":1,"interval":1,"start_time":1612095722345},{"elapsed_time":3604253,"segment":1,"interval":1,"start_time":1612095722473},{"elapsed_time":3610122,"segment":1,"interval":1,"start_time":1612095728342},{"elapsed_time":3620122,"segment":1,"interval":1,"start_time":1612095738342},{"elapsed_time":3634122,"segment":1,"interval":1,"start_time":1612095752342},{"elapsed_time":3644127,"segment":1,"interval":1,"start_time":1612095762347},{"elapsed_time":3654131,"segment":1,"interval":1,"start_time":1612095772351},{"elapsed_time":3665129,"segment":1,"interval":1,"start_time":1612095783349},{"elapsed_time":3675123,"segment":1,"interval":1,"start_time":1612095793343},{"elapsed_time":3684125,"segment":1,"interval":1,"start_time":1612095802345},{"elapsed_time":3692751,"segment":1,"interval":1,"start_time":1612095810971},{"elapsed_time":3694145,"segment":1,"interval":1,"start_time":1612095812365},{"elapsed_time":3695003,"segment":1,"interval":1,"start_time":1612095813223},{"elapsed_time":3700128,"segment":1,"interval":1,"start_time":1612095818348},{"elapsed_time":3710126,"segment":1,"interval":1,"start_time":1612095828346},{"elapsed_time":3719007,"segment":1,"interval":1,"start_time":1612095837227},{"elapsed_time":3720007,"segment":1,"interval":1,"start_time":1612095838227},{"elapsed_time":3729123,"segment":1,"interval":1,"start_time":1612095847343},{"elapsed_time":3734123,"segment":1,"interval":1,"start_time":1612095852343},{"elapsed_time":3744139,"segment":1,"interval":1,"start_time":1612095862359},{"elapsed_time":3744670,"segment":1,"interval":1,"start_time":1612095864760}]