[{"heart_rate":58.0,"heart_rate_max":63.0,"heart_rate_min":53.0,"start_time":1614150000000,"end_time":1614150059000},{"heart_rate":56.0,"heart_rate_max":60.0,"heart_rate_min":53.0,"start_time":1614150060000,"end_time":1614150119000},{"heart_rate":60.0,"heart_rate_max":65.0,"heart_rate_min":57.0,"start_time":1614150120000,"end_time":1614150179000},{"heart_rate":58.0,"heart_rate_max":60.0,"heart_rate_min":55.0,"start_time":1614150180000,"end_time":1614150239000},{"heart_rate":60.0,"heart_rate_max":63.0,"heart_rate_min":58.0,"start_time":1614150240000,"end_time":1614150299000},{"heart_rate":56.0,"heart_rate_max":59.0,"heart_rate_min":56.0,"start_time":1614150300000,"end_time":1614150359000},{"heart_rate":58.0,"heart_rate_max":61.0,"heart_rate_min":55.0,"start_time":1614150360000,"end_time":1614150419000},{"heart_rate":59.0,"heart_rate_max":61.0,"heart_rate_min":56.0,"start_time":1614150420000,"end_time":1614150479000},{"heart_rate":60.0,"heart_rate_max":62.0,"heart_rate_min":59.0,"start_time":1614150480000,"end_time":1614150539000},{"heart_rate":58.0,"heart_rate_max":60.0,"heart_rate_min":57.0,"start_time":1614150540000,"end_time":1614150599000},{"heart_rate":58.0,"heart_rate_max":59.0,"heart_rate_min":58.0,"start_time":1614150600000,"end_time":1614150659000},{"heart_rate":58.0,"heart_rate_max":60.0,"heart_rate_min":58.0,"start_time":1614150660000,"end_time":1614150719000},{"heart_rate":57.0,"heart_rate_max":59.0,"heart_rate_min":54.0,"start_time":1614150720000,"end_time":1614150779000},{"heart_rate":52.0,"heart_rate_max":54.0,"heart_rate_min":50.0,"start_time":1614150780000,"end_time":1614150839000},{"heart_rate":52.0,"heart_rate_max":54.0,"heart_rate_min":50.0,"start_time":1614150840000,"end_time":1614150899000},{"heart_rate":58.0,"heart_rate_max":65.0,"heart_rate_min":53.0,"start_time":1614150900000,"end_time":1614150959000},{"heart_rate":52.0,"heart_rate_max":58.0,"heart_rate_min":48.0,"start_time":1614150960000,"end_time":1614151019000},{"heart_rate":51.0,"heart_rate_max":84.0,"heart_rate_min":48.0,"start_time":1614151020000,"end_time":1614151079000},{"heart_rate":84.0,"heart_rate_max":84.0,"heart_rate_min":84.0,"start_time":1614151080000,"end_time":1614151139000},{"heart_rate":69.0,"heart_rate_max":75.0,"heart_rate_min":60.0,"start_time":1614151140000,"end_time":1614151199000},{"heart_rate":56.0,"heart_rate_max":61.0,"heart_rate_min":54.0,"start_time":1614151200000,"end_time":1614151259000},{"heart_rate":62.0,"heart_rate_max":74.0,"heart_rate_min":54.0,"start_time":1614151260000,"end_time":1614151319000},{"heart_rate":56.0,"heart_rate_max":60.0,"heart_rate_min":53.0,"start_time":1614151320000,"end_time":1614151379000},{"heart_rate":58.0,"heart_rate_max":67.0,"heart_rate_min":56.0,"start_time":1614151380000,"end_time":1614151439000},{"heart_rate":59.0,"heart_rate_max":64.0,"heart_rate_min":55.0,"start_time":1614151440000,"end_time":1614151499000},{"heart_rate":56.0,"heart_rate_max":60.0,"heart_rate_min":52.0,"start_time":1614151500000,"end_time":1614151559000},{"heart_rate":55.0,"heart_rate_max":58.0,"heart_rate_min":53.0,"start_time":1614151560000,"end_time":1614151619000},{"heart_rate":56.0,"heart_rate_max":61.0,"heart_rate_min":54.0,"start_time":1614151620000,"end_time":1614151679000},{"heart_rate":55.0,"heart_rate_max":57.0,"heart_rate_min":53.0,"start_time":1614151680000,"end_time":1614151739000},{"heart_rate":54.0,"heart_rate_max":57.0,"heart_rate_min":53.0,"start_time":1614151740000,"end_time":1614151799000},{"heart_rate":56.0,"heart_rate_max":60.0,"heart_rate_min":54.0,"start_time":1614151800000,"end_time":1614151859000},{"heart_rate":62.0,"heart_rate_max":68.0,"heart_rate_min":59.0,"start_time":1614151860000,"end_time":1614151919000},{"heart_rate":57.0,"heart_rate_max":62.0,"heart_rate_min":55.0,"start_time":1614151920000,"end_time":1614151979000},{"heart_rate":59.0,"heart_rate_max":67.0,"heart_rate_min":55.0,"start_time":1614151980000,"end_time":1614152039000},{"heart_rate":67.0,"heart_rate_max":69.0,"heart_rate_min":66.0,"start_time":1614152040000,"end_time":1614152099000},{"heart_rate":64.0,"heart_rate_max":69.0,"heart_rate_min":62.0,"start_time":1614152100000,"end_time":1614152159000},{"heart_rate":69.0,"heart_rate_max":76.0,"heart_rate_min":66.0,"start_time":1614152160000,"end_time":1614152219000},{"heart_rate":67.0,"heart_rate_max":73.0,"heart_rate_min":64.0,"start_time":1614152220000,"end_time":1614152279000},{"heart_rate":64.0,"heart_rate_max":67.0,"heart_rate_min":60.0,"start_time":1614152280000,"end_time":1614152339000},{"heart_rate":67.0,"heart_rate_max":76.0,"heart_rate_min":63.0,"start_time":1614152340000,"end_time":1614152399000},{"heart_rate":75.0,"heart_rate_max":77.0,"heart_rate_min":74.0,"start_time":1614152400000,"end_time":1614152459000},{"heart_rate":75.0,"heart_rate_max":76.0,"heart_rate_min":75.0,"start_time":1614152460000,"end_time":1614152519000},{"heart_rate":77.0,"heart_rate_max":81.0,"heart_rate_min":73.0,"start_time":1614152520000,"end_time":1614152579000},{"heart_rate":63.0,"heart_rate_max":68.0,"heart_rate_min":61.0,"start_time":1614152580000,"end_time":1614152639000},{"heart_rate":62.0,"heart_rate_max":65.0,"heart_rate_min":59.0,"start_time":1614152640000,"end_time":1614152699000},{"heart_rate":60.0,"heart_rate_max":62.0,"heart_rate_min":59.0,"start_time":1614152700000,"end_time":1614152759000},{"heart_rate":63.0,"heart_rate_max":69.0,"heart_rate_min":58.0,"start_time":1614152760000,"end_time":1614152819000},{"heart_rate":69.0,"heart_rate_max":74.0,"heart_rate_min":64.0,"start_time":1614152820000,"end_time":1614152879000},{"heart_rate":77.0,"heart_rate_max":80.0,"heart_rate_min":73.0,"start_time":1614153000000,"end_time":1614153059000},{"heart_rate":69.0,"heart_rate_max":79.0,"heart_rate_min":66.0,"start_time":1614153060000,"end_time":1614153119000},{"heart_rate":74.0,"heart_rate_max":77.0,"heart_rate_min":70.0,"start_time":1614153120000,"end_time":1614153179000},{"heart_rate":71.0,"heart_rate_max":77.0,"heart_rate_min":67.0,"start_time":1614153180000,"end_time":1614153239000},{"heart_rate":73.0,"heart_rate_max":78.0,"heart_rate_min":70.0,"start_time":1614153240000,"end_time":1614153299000},{"heart_rate":75.0,"heart_rate_max":82.0,"heart_rate_min":69.0,"start_time":1614153300000,"end_time":1614153359000},{"heart_rate":66.0,"heart_rate_max":70.0,"heart_rate_min":61.0,"start_time":1614153360000,"end_time":1614153419000},{"heart_rate":67.0,"heart_rate_max":71.0,"heart_rate_min":62.0,"start_time":1614153420000,"end_time":1614153479000},{"heart_rate":68.0,"heart_rate_max":77.0,"heart_rate_min":62.0,"start_time":1614153480000,"end_time":1614153539000},{"heart_rate":71.0,"heart_rate_max":76.0,"heart_rate_min":65.0,"start_time":1614153540000,"end_time":1614153599000}]