[{"heart_rate":90.0,"heart_rate_max":96.0,"heart_rate_min":79.0,"start_time":1609541640000,"end_time":1609541699000},{"heart_rate":83.0,"heart_rate_max":87.0,"heart_rate_min":79.0,"start_time":1609541700000,"end_time":1609541759000},{"heart_rate":84.0,"heart_rate_max":88.0,"heart_rate_min":81.0,"start_time":1609541760000,"end_time":1609541819000},{"heart_rate":85.0,"heart_rate_max":89.0,"heart_rate_min":79.0,"start_time":1609541820000,"end_time":1609541879000},{"heart_rate":90.0,"heart_rate_max":90.0,"heart_rate_min":90.0,"start_time":1609541880000,"end_time":1609541939000},{"heart_rate":85.0,"heart_rate_max":90.0,"heart_rate_min":81.0,"start_time":1609541940000,"end_time":1609541999000}]