{"data":[{"advanced_metrics":[{"chart_data":[{"duration":10000,"score":0,"value":0.8173},{"duration":20000,"score":1,"value":0.9081},{"duration":30000,"score":2,"value":0.9717},{"duration":40000,"score":2,"value":0.9871},{"duration":50000,"score":2,"value":0.9749},{"duration":60000,"score":2,"value":0.9782},{"duration":70000,"score":2,"value":0.9743},{"duration":80000,"score":2,"value":0.9685},{"duration":90000,"score":2,"value":0.9645},{"duration":100000,"score":2,"value":0.9858},{"duration":110000,"score":2,"value":0.9957},{"duration":120000,"score":2,"value":0.9988},{"duration":130000,"score":2,"value":0.9897},{"duration":140000,"score":2,"value":0.9611},{"duration":150000,"score":1,"value":0.9432},{"duration":160000,"score":2,"value":0.9593},{"duration":170000,"score":2,"value":0.9862},{"duration":180000,"score":2,"value":0.9974},{"duration":190000,"score":2,"value":0.9755},{"duration":200000,"score":2,"value":0.9639},{"duration":210000,"score":2,"value":0.9820},{"duration":220000,"score":2,"value":0.9751},{"duration":230000,"score":2,"value":0.9762},{"duration":240000,"score":2,"value":0.9840},{"duration":250000,"score":2,"value":0.9919},{"duration":260000,"score":2,"value":0.9959},{"duration":270000,"score":2,"value":0.9891},{"duration":280000,"score":2,"value":0.9828},{"duration":290000,"score":2,"value":0.9780},{"duration":300000,"score":2,"value":0.9688},{"duration":310000,"score":1,"value":0.9057},{"duration":320000,"score":0,"value":0.8800},{"duration":330000,"score":1,"value":0.9170},{"duration":340000,"score":2,"value":0.9535},{"duration":350000,"score":2,"value":0.9545},{"duration":360000,"score":1,"value":0.9299},{"duration":370000,"score":1,"value":0.9444},{"duration":380000,"score":2,"value":0.9708},{"duration":390000,"score":2,"value":0.9675},{"duration":400000,"score":2,"value":0.9601},{"duration":410000,"score":2,"value":0.9623},{"duration":420000,"score":2,"value":0.9763},{"duration":430000,"score":2,"value":0.9780},{"duration":440000,"score":2,"value":0.9812},{"duration":450000,"score":2,"value":0.9800},{"duration":460000,"score":2,"value":0.9716},{"duration":470000,"score":2,"value":0.9615},{"duration":480000,"score":2,"value":0.9603},{"duration":490000,"score":2,"value":0.9656},{"duration":500000,"score":2,"value":0.9643},{"duration":510000,"score":2,"value":0.9715},{"duration":520000,"score":2,"value":0.9794},{"duration":530000,"score":2,"value":0.9725},{"duration":540000,"score":2,"value":0.9676},{"duration":550000,"score":2,"value":0.9774},{"duration":560000,"score":2,"value":0.9912},{"duration":570000,"score":2,"value":0.9803},{"duration":580000,"score":1,"value":0.9180},{"duration":590000,"score":0,"value":0.8540},{"duration":600000,"score":1,"value":0.9257},{"duration":610000,"score":1,"value":0.9369},{"duration":620000,"score":1,"value":0.9252},{"duration":630000,"score":2,"value":0.9530},{"duration":640000,"score":2,"value":0.9658},{"duration":650000,"score":2,"value":0.9782},{"duration":660000,"score":2,"value":0.9778},{"duration":670000,"score":2,"value":0.9587},{"duration":680000,"score":2,"value":0.9690},{"duration":690000,"score":2,"value":0.9691},{"duration":700000,"score":2,"value":0.9580},{"duration":710000,"score":2,"value":0.9579},{"duration":720000,"score":1,"value":0.9478},{"duration":730000,"score":2,"value":0.9637},{"duration":740000,"score":2,"value":0.9768},{"duration":750000,"score":2,"value":0.9812},{"duration":760000,"score":2,"value":0.9540},{"duration":770000,"score":1,"value":0.9487},{"duration":780000,"score":2,"value":0.9741},{"duration":790000,"score":2,"value":0.9735},{"duration":800000,"score":2,"value":0.9704},{"duration":810000,"score":2,"value":0.9744},{"duration":820000,"score":2,"value":0.9720},{"duration":830000,"score":2,"value":0.9811},{"duration":840000,"score":2,"value":0.9869},{"duration":850000,"score":2,"value":0.9710},{"duration":860000,"score":2,"value":0.9760},{"duration":870000,"score":2,"value":0.9817},{"duration":880000,"score":2,"value":0.9804},{"duration":890000,"score":2,"value":0.9748},{"duration":900000,"score":2,"value":0.9711},{"duration":910000,"score":2,"value":0.9670},{"duration":920000,"score":2,"value":0.9577},{"duration":930000,"score":2,"value":0.9572},{"duration":940000,"score":2,"value":0.9791},{"duration":950000,"score":2,"value":0.9892},{"duration":960000,"score":2,"value":0.9847},{"duration":970000,"score":2,"value":0.9821},{"duration":979999,"score":2,"value":0.9834},{"duration":989999,"score":2,"value":0.9743},{"duration":999999,"score":2,"value":0.9754},{"duration":1009999,"score":2,"value":0.9815},{"duration":1019999,"score":2,"value":0.9877},{"duration":1029999,"score":2,"value":0.9973},{"duration":1039999,"score":2,"value":0.9819},{"duration":1049999,"score":1,"value":0.9404},{"duration":1067559,"score":0,"value":0.5435},{"duration":1077559,"score":0,"value":0.4526},{"duration":1087559,"score":0,"value":0.8776},{"duration":1097559,"score":2,"value":0.9570},{"duration":1107559,"score":2,"value":0.9768},{"duration":1117559,"score":2,"value":0.9805},{"duration":1127559,"score":2,"value":0.9779},{"duration":1137559,"score":2,"value":0.9601},{"duration":1147559,"score":2,"value":0.9681},{"duration":1157559,"score":2,"value":0.9768},{"duration":1167559,"score":2,"value":0.9653},{"duration":1177559,"score":2,"value":0.9617},{"duration":1187559,"score":2,"value":0.9804},{"duration":1197559,"score":2,"value":0.9921},{"duration":1207559,"score":2,"value":0.9881},{"duration":1217559,"score":2,"value":0.9808},{"duration":1227559,"score":2,"value":0.9754},{"duration":1237559,"score":2,"value":0.9711},{"duration":1247559,"score":2,"value":0.9692},{"duration":1257559,"score":2,"value":0.9805},{"duration":1267559,"score":2,"value":0.9892},{"duration":1277559,"score":2,"value":0.9778},{"duration":1287559,"score":2,"value":0.9607},{"duration":1297559,"score":2,"value":0.9608},{"duration":1307559,"score":2,"value":0.9655},{"duration":1317559,"score":2,"value":0.9663},{"duration":1327559,"score":2,"value":0.9630},{"duration":1337559,"score":2,"value":0.9847},{"duration":1347559,"score":2,"value":0.9896},{"duration":1357559,"score":2,"value":0.9827},{"duration":1367559,"score":2,"value":0.9630},{"duration":1377559,"score":2,"value":0.9578},{"duration":1387559,"score":1,"value":0.9070},{"duration":1397559,"score":0,"value":0.8887},{"duration":1407559,"score":2,"value":0.9547},{"duration":1417559,"score":2,"value":0.9669},{"duration":1427559,"score":2,"value":0.9775},{"duration":1437559,"score":2,"value":0.9870},{"duration":1447559,"score":2,"value":0.9924},{"duration":1457559,"score":2,"value":0.9984},{"duration":1467559,"score":2,"value":0.9934},{"duration":1477559,"score":2,"value":0.9826},{"duration":1487559,"score":2,"value":0.9830},{"duration":1497559,"score":2,"value":0.9902},{"duration":1507559,"score":2,"value":0.9847},{"duration":1517559,"score":2,"value":0.9699},{"duration":1527559,"score":2,"value":0.9665},{"duration":1537559,"score":2,"value":0.9738},{"duration":1547559,"score":2,"value":0.9827},{"duration":1557559,"score":2,"value":0.9937},{"duration":1567559,"score":2,"value":0.9950},{"duration":1577559,"score":2,"value":0.9991},{"duration":1587559,"score":2,"value":0.9998},{"duration":1597559,"score":2,"value":0.9958},{"duration":1607559,"score":2,"value":0.9967},{"duration":1617559,"score":2,"value":0.9892},{"duration":1627559,"score":2,"value":0.9785},{"duration":1637559,"score":2,"value":0.9522},{"duration":1647559,"score":2,"value":0.9616},{"duration":1657559,"score":2,"value":0.9852},{"duration":1667559,"score":2,"value":0.9942},{"duration":1677559,"score":2,"value":0.9937},{"duration":1687559,"score":2,"value":0.9918},{"duration":1697559,"score":2,"value":0.9603},{"duration":1707559,"score":2,"value":0.9695},{"duration":1717559,"score":2,"value":0.9807},{"duration":1727559,"score":2,"value":0.9745}],"data_type":"regularity","overall_score":2,"score_ratio":[4.0,8.0,88.0]},{"chart_data":[{"duration":10000,"score":2,"value":-0.0034},{"duration":20000,"score":2,"value":-0.0163},{"duration":30000,"score":2,"value":-0.0088},{"duration":40000,"score":1,"value":-0.0270},{"duration":50000,"score":1,"value":-0.0257},{"duration":60000,"score":1,"value":-0.0234},{"duration":70000,"score":2,"value":-0.0174},{"duration":80000,"score":2,"value":-0.0216},{"duration":90000,"score":2,"value":-0.0165},{"duration":100000,"score":2,"value":-0.0208},{"duration":110000,"score":2,"value":-0.0223},{"duration":120000,"score":2,"value":-0.0189},{"duration":130000,"score":2,"value":-0.0211},{"duration":140000,"score":2,"value":-0.0178},{"duration":150000,"score":2,"value":-0.0162},{"duration":160000,"score":1,"value":-0.0245},{"duration":170000,"score":1,"value":-0.0411},{"duration":180000,"score":1,"value":-0.0296},{"duration":190000,"score":1,"value":-0.0256},{"duration":200000,"score":1,"value":-0.0232},{"duration":210000,"score":1,"value":-0.0300},{"duration":220000,"score":2,"value":0.0037},{"duration":230000,"score":2,"value":-0.0162},{"duration":240000,"score":1,"value":-0.0320},{"duration":250000,"score":1,"value":-0.0298},{"duration":260000,"score":1,"value":-0.0240},{"duration":270000,"score":2,"value":-0.0198},{"duration":280000,"score":1,"value":-0.0364},{"duration":290000,"score":1,"value":-0.0422},{"duration":300000,"score":2,"value":-0.0135},{"duration":310000,"score":2,"value":-0.0171},{"duration":320000,"score":1,"value":-0.0312},{"duration":330000,"score":1,"value":-0.0275},{"duration":340000,"score":1,"value":-0.0256},{"duration":350000,"score":2,"value":-0.0174},{"duration":360000,"score":1,"value":-0.0342},{"duration":370000,"score":2,"value":-0.0135},{"duration":380000,"score":2,"value":-0.0172},{"duration":390000,"score":2,"value":-0.0004},{"duration":400000,"score":2,"value":-0.0098},{"duration":410000,"score":2,"value":-0.0157},{"duration":420000,"score":2,"value":-0.0128},{"duration":430000,"score":2,"value":-0.0106},{"duration":440000,"score":1,"value":-0.0268},{"duration":450000,"score":2,"value":-0.0147},{"duration":460000,"score":1,"value":-0.0314},{"duration":470000,"score":2,"value":-0.0016},{"duration":480000,"score":2,"value":-0.0064},{"duration":490000,"score":2,"value":0.0045},{"duration":500000,"score":2,"value":-0.0136},{"duration":510000,"score":2,"value":-0.0211},{"duration":520000,"score":1,"value":-0.0247},{"duration":530000,"score":2,"value":-0.0210},{"duration":540000,"score":2,"value":-0.0211},{"duration":550000,"score":2,"value":-0.0172},{"duration":560000,"score":2,"value":-0.0105},{"duration":570000,"score":2,"value":-0.0204},{"duration":580000,"score":0,"value":-0.0851},{"duration":590000,"score":1,"value":-0.0327},{"duration":600000,"score":2,"value":-0.0151},{"duration":610000,"score":2,"value":0.0052},{"duration":620000,"score":2,"value":-0.0116},{"duration":630000,"score":2,"value":-0.0152},{"duration":640000,"score":2,"value":-0.0111},{"duration":650000,"score":2,"value":-0.0058},{"duration":660000,"score":2,"value":-0.0191},{"duration":670000,"score":2,"value":-0.0111},{"duration":680000,"score":2,"value":-0.0039},{"duration":690000,"score":2,"value":-0.0149},{"duration":700000,"score":2,"value":-0.0052},{"duration":710000,"score":2,"value":-0.0016},{"duration":720000,"score":2,"value":-0.0115},{"duration":730000,"score":2,"value":-0.0030},{"duration":740000,"score":2,"value":-0.0095},{"duration":750000,"score":2,"value":-0.0091},{"duration":760000,"score":2,"value":-0.0137},{"duration":770000,"score":2,"value":-0.0157},{"duration":780000,"score":2,"value":-0.0138},{"duration":790000,"score":1,"value":-0.0262},{"duration":800000,"score":1,"value":-0.0257},{"duration":810000,"score":2,"value":-0.0159},{"duration":820000,"score":2,"value":-0.0219},{"duration":830000,"score":2,"value":-0.0138},{"duration":840000,"score":2,"value":-0.0189},{"duration":850000,"score":2,"value":-0.0028},{"duration":860000,"score":2,"value":-0.0173},{"duration":870000,"score":2,"value":-0.0155},{"duration":880000,"score":2,"value":-0.0062},{"duration":890000,"score":2,"value":-0.0202},{"duration":900000,"score":2,"value":-0.0199},{"duration":910000,"score":2,"value":-0.0078},{"duration":920000,"score":2,"value":-0.0095},{"duration":930000,"score":2,"value":-0.0123},{"duration":940000,"score":2,"value":-0.0102},{"duration":950000,"score":2,"value":-0.0132},{"duration":960000,"score":2,"value":-0.0194},{"duration":970000,"score":1,"value":-0.0241},{"duration":979999,"score":2,"value":-0.0100},{"duration":989999,"score":2,"value":-0.0109},{"duration":999999,"score":2,"value":-0.0126},{"duration":1009999,"score":2,"value":-0.0142},{"duration":1019999,"score":2,"value":-0.0071},{"duration":1029999,"score":2,"value":-0.0108},{"duration":1039999,"score":2,"value":-0.0074},{"duration":1049999,"score":2,"value":-0.0149},{"duration":1067559,"score":2,"value":-0.0125},{"duration":1077559,"score":2,"value":-0.0093},{"duration":1087559,"score":2,"value":-0.0100},{"duration":1097559,"score":2,"value":-0.0025},{"duration":1107559,"score":2,"value":-0.0041},{"duration":1117559,"score":1,"value":-0.0293},{"duration":1127559,"score":2,"value":-0.0181},{"duration":1137559,"score":2,"value":-0.0160},{"duration":1147559,"score":2,"value":-0.0130},{"duration":1157559,"score":2,"value":-0.0112},{"duration":1167559,"score":2,"value":-0.0144},{"duration":1177559,"score":2,"value":-0.0171},{"duration":1187559,"score":2,"value":-0.0141},{"duration":1197559,"score":2,"value":-0.0166},{"duration":1207559,"score":2,"value":-0.0119},{"duration":1217559,"score":2,"value":-0.0160},{"duration":1227559,"score":2,"value":-0.0175},{"duration":1237559,"score":2,"value":-0.0092},{"duration":1247559,"score":2,"value":-0.0175},{"duration":1257559,"score":2,"value":-0.0205},{"duration":1267559,"score":2,"value":-0.0206},{"duration":1277559,"score":2,"value":-0.0188},{"duration":1287559,"score":1,"value":-0.0241},{"duration":1297559,"score":2,"value":-0.0173},{"duration":1307559,"score":2,"value":-0.0164},{"duration":1317559,"score":2,"value":-0.0225},{"duration":1327559,"score":2,"value":-0.0100},{"duration":1337559,"score":2,"value":-0.0159},{"duration":1347559,"score":2,"value":-0.0198},{"duration":1357559,"score":2,"value":-0.0168},{"duration":1367559,"score":1,"value":-0.0271},{"duration":1377559,"score":2,"value":-0.0183},{"duration":1387559,"score":2,"value":-0.0148},{"duration":1397559,"score":2,"value":-0.0119},{"duration":1407559,"score":2,"value":-0.0127},{"duration":1417559,"score":2,"value":-0.0121},{"duration":1427559,"score":2,"value":-0.0039},{"duration":1437559,"score":2,"value":-0.0137},{"duration":1447559,"score":2,"value":-0.0146},{"duration":1457559,"score":2,"value":-0.0131},{"duration":1467559,"score":2,"value":-0.0117},{"duration":1477559,"score":2,"value":-0.0123},{"duration":1487559,"score":2,"value":-0.0176},{"duration":1497559,"score":2,"value":-0.0114},{"duration":1507559,"score":2,"value":-0.0182},{"duration":1517559,"score":1,"value":-0.0235},{"duration":1527559,"score":2,"value":-0.0224},{"duration":1537559,"score":2,"value":-0.0174},{"duration":1547559,"score":2,"value":-0.0154},{"duration":1557559,"score":2,"value":-0.0148},{"duration":1567559,"score":2,"value":-0.0101},{"duration":1577559,"score":2,"value":-0.0174},{"duration":1587559,"score":2,"value":-0.0199},{"duration":1597559,"score":2,"value":-0.0157},{"duration":1607559,"score":2,"value":-0.0170},{"duration":1617559,"score":2,"value":-0.0089},{"duration":1627559,"score":2,"value":-0.0048},{"duration":1637559,"score":2,"value":-0.0045},{"duration":1647559,"score":2,"value":-0.0141},{"duration":1657559,"score":2,"value":-0.0144},{"duration":1667559,"score":2,"value":-0.0146},{"duration":1677559,"score":2,"value":-0.0159},{"duration":1687559,"score":2,"value":-0.0168},{"duration":1697559,"score":2,"value":-0.0176},{"duration":1707559,"score":2,"value":-0.0170},{"duration":1717559,"score":2,"value":-0.0204},{"duration":1727559,"score":1,"value":-0.0273}],"data_type":"asymmetry","overall_score":2,"score_ratio":[3.0,24.0,73.0]},{"chart_data":[{"duration":10000,"score":0,"value":35142.1796},{"duration":20000,"score":0,"value":39518.7695},{"duration":30000,"score":0,"value":39928.9921},{"duration":40000,"score":0,"value":38362.4062},{"duration":50000,"score":0,"value":39449.9648},{"duration":60000,"score":0,"value":37296.6562},{"duration":70000,"score":0,"value":36592.4101},{"duration":80000,"score":0,"value":37447.5546},{"duration":90000,"score":0,"value":37455.7851},{"duration":100000,"score":0,"value":37668.9414},{"duration":110000,"score":0,"value":38049.8085},{"duration":120000,"score":0,"value":37825.2187},{"duration":130000,"score":0,"value":37353.9101},{"duration":140000,"score":0,"value":37148.1835},{"duration":150000,"score":0,"value":37853.3632},{"duration":160000,"score":0,"value":37342.9804},{"duration":170000,"score":0,"value":37671.2968},{"duration":180000,"score":0,"value":37155.5703},{"duration":190000,"score":0,"value":37159.0390},{"duration":200000,"score":0,"value":38090.6835},{"duration":210000,"score":0,"value":37944.8515},{"duration":220000,"score":0,"value":37482.5898},{"duration":230000,"score":0,"value":37115.2773},{"duration":240000,"score":0,"value":36083.6914},{"duration":250000,"score":0,"value":36565.8593},{"duration":260000,"score":0,"value":36640.8710},{"duration":270000,"score":0,"value":36985.9531},{"duration":280000,"score":0,"value":36697.7695},{"duration":290000,"score":0,"value":36792.2929},{"duration":300000,"score":0,"value":37239.9726},{"duration":310000,"score":0,"value":37349.2148},{"duration":320000,"score":0,"value":37707.8085},{"duration":330000,"score":0,"value":38110.3437},{"duration":340000,"score":0,"value":36444.8867},{"duration":350000,"score":0,"value":36194.1718},{"duration":360000,"score":0,"value":35759.9492},{"duration":370000,"score":0,"value":35964.6718},{"duration":380000,"score":0,"value":36427.8007},{"duration":390000,"score":0,"value":36157.4921},{"duration":400000,"score":0,"value":37528.4921},{"duration":410000,"score":0,"value":37071.2343},{"duration":420000,"score":0,"value":36824.7109},{"duration":430000,"score":0,"value":38275.2226},{"duration":440000,"score":0,"value":37421.3671},{"duration":450000,"score":0,"value":38120.8242},{"duration":460000,"score":0,"value":37279.1484},{"duration":470000,"score":0,"value":36495.0117},{"duration":480000,"score":0,"value":36855.0273},{"duration":490000,"score":0,"value":36980.3203},{"duration":500000,"score":0,"value":36372.3906},{"duration":510000,"score":0,"value":37726.6796},{"duration":520000,"score":0,"value":37055.5781},{"duration":530000,"score":0,"value":37099.1523},{"duration":540000,"score":0,"value":38272.8437},{"duration":550000,"score":0,"value":37691.1328},{"duration":560000,"score":0,"value":37155.1171},{"duration":570000,"score":0,"value":36828.6757},{"duration":580000,"score":0,"value":35303.7031},{"duration":590000,"score":0,"value":36851.9921},{"duration":600000,"score":0,"value":36965.2070},{"duration":610000,"score":0,"value":37246.9453},{"duration":620000,"score":0,"value":34591.2304},{"duration":630000,"score":0,"value":34976.9687},{"duration":640000,"score":0,"value":36733.4804},{"duration":650000,"score":0,"value":37592.2109},{"duration":660000,"score":0,"value":36844.8164},{"duration":670000,"score":0,"value":36938.1992},{"duration":680000,"score":0,"value":36842.2734},{"duration":690000,"score":0,"value":36736.9609},{"duration":700000,"score":0,"value":35072.1562},{"duration":710000,"score":0,"value":36126.8437},{"duration":720000,"score":0,"value":36711.3906},{"duration":730000,"score":0,"value":36077.9414},{"duration":740000,"score":0,"value":36347.5390},{"duration":750000,"score":0,"value":35898.6445},{"duration":760000,"score":0,"value":40185.2929},{"duration":770000,"score":0,"value":37190.4101},{"duration":780000,"score":0,"value":36011.6523},{"duration":790000,"score":0,"value":36227.8945},{"duration":800000,"score":0,"value":37313.9375},{"duration":810000,"score":0,"value":37740.4453},{"duration":820000,"score":0,"value":38536.3398},{"duration":830000,"score":0,"value":36843.0898},{"duration":840000,"score":0,"value":37296.1093},{"duration":850000,"score":0,"value":36844.6757},{"duration":860000,"score":0,"value":35111.8281},{"duration":870000,"score":0,"value":37168.7812},{"duration":880000,"score":0,"value":36928.0507},{"duration":890000,"score":0,"value":35889.8046},{"duration":900000,"score":0,"value":35382.3593},{"duration":910000,"score":0,"value":34323.5273},{"duration":920000,"score":0,"value":37663.8281},{"duration":930000,"score":0,"value":37908.7421},{"duration":940000,"score":0,"value":36980.9453},{"duration":950000,"score":0,"value":37036.0},{"duration":960000,"score":0,"value":36566.1601},{"duration":970000,"score":0,"value":36665.9609},{"duration":979999,"score":0,"value":36272.4296},{"duration":989999,"score":0,"value":37207.6562},{"duration":999999,"score":0,"value":36578.0937},{"duration":1009999,"score":0,"value":35974.3710},{"duration":1019999,"score":0,"value":36315.1132},{"duration":1029999,"score":0,"value":34703.0468},{"duration":1039999,"score":0,"value":35634.7539},{"duration":1049999,"score":0,"value":35172.1171},{"duration":1067559,"score":1,"value":43186.3867},{"duration":1077559,"score":1,"value":38894.6132},{"duration":1087559,"score":0,"value":38252.6406},{"duration":1097559,"score":0,"value":37866.7968},{"duration":1107559,"score":0,"value":38548.9179},{"duration":1117559,"score":0,"value":38913.2656},{"duration":1127559,"score":0,"value":38576.2890},{"duration":1137559,"score":0,"value":38230.5859},{"duration":1147559,"score":0,"value":38053.0273},{"duration":1157559,"score":0,"value":38880.3710},{"duration":1167559,"score":0,"value":38132.1484},{"duration":1177559,"score":0,"value":38762.3906},{"duration":1187559,"score":0,"value":38694.1093},{"duration":1197559,"score":0,"value":38963.4296},{"duration":1207559,"score":0,"value":40602.1679},{"duration":1217559,"score":0,"value":37982.5156},{"duration":1227559,"score":0,"value":38802.0703},{"duration":1237559,"score":0,"value":38837.8828},{"duration":1247559,"score":0,"value":38163.7460},{"duration":1257559,"score":0,"value":38630.8281},{"duration":1267559,"score":0,"value":39028.0195},{"duration":1277559,"score":0,"value":38922.9414},{"duration":1287559,"score":0,"value":38526.0195},{"duration":1297559,"score":0,"value":37554.6445},{"duration":1307559,"score":0,"value":37248.9804},{"duration":1317559,"score":0,"value":37816.4804},{"duration":1327559,"score":0,"value":38081.8320},{"duration":1337559,"score":0,"value":38958.0468},{"duration":1347559,"score":0,"value":38678.9960},{"duration":1357559,"score":0,"value":39037.6171},{"duration":1367559,"score":0,"value":36933.0820},{"duration":1377559,"score":0,"value":36080.2656},{"duration":1387559,"score":0,"value":39328.25},{"duration":1397559,"score":0,"value":39733.9335},{"duration":1407559,"score":0,"value":36838.0273},{"duration":1417559,"score":0,"value":39627.5117},{"duration":1427559,"score":0,"value":39057.6796},{"duration":1437559,"score":0,"value":38201.0937},{"duration":1447559,"score":0,"value":37266.1406},{"duration":1457559,"score":0,"value":37380.7421},{"duration":1467559,"score":0,"value":37612.0898},{"duration":1477559,"score":0,"value":37866.7343},{"duration":1487559,"score":0,"value":38331.2109},{"duration":1497559,"score":0,"value":39017.7890},{"duration":1507559,"score":0,"value":36853.4531},{"duration":1517559,"score":0,"value":38479.1757},{"duration":1527559,"score":0,"value":38454.4765},{"duration":1537559,"score":0,"value":38080.2656},{"duration":1547559,"score":0,"value":36844.3906},{"duration":1557559,"score":0,"value":38324.5273},{"duration":1567559,"score":0,"value":39314.6992},{"duration":1577559,"score":0,"value":39156.4843},{"duration":1587559,"score":0,"value":37072.0898},{"duration":1597559,"score":0,"value":37085.1757},{"duration":1607559,"score":0,"value":37798.4140},{"duration":1617559,"score":0,"value":36556.8789},{"duration":1627559,"score":0,"value":40450.5625},{"duration":1637559,"score":0,"value":39343.8945},{"duration":1647559,"score":0,"value":38687.7968},{"duration":1657559,"score":0,"value":39808.2382},{"duration":1667559,"score":0,"value":39456.5468},{"duration":1677559,"score":0,"value":39206.9375},{"duration":1687559,"score":0,"value":40198.4648},{"duration":1697559,"score":0,"value":42179.8906},{"duration":1707559,"score":0,"value":41572.8437},{"duration":1717559,"score":0,"value":41193.7656},{"duration":1727559,"score":0,"value":41760.0937}],"data_type":"stiffness","overall_score":0,"score_ratio":[95.0,4.0,1.0]},{"chart_data":[{"duration":10000,"score":2,"value":0.0777},{"duration":20000,"score":1,"value":0.0915},{"duration":30000,"score":0,"value":0.0950},{"duration":40000,"score":0,"value":0.0962},{"duration":50000,"score":0,"value":0.0942},{"duration":60000,"score":0,"value":0.0948},{"duration":70000,"score":0,"value":0.0986},{"duration":80000,"score":0,"value":0.0957},{"duration":90000,"score":0,"value":0.0959},{"duration":100000,"score":0,"value":0.0945},{"duration":110000,"score":0,"value":0.0937},{"duration":120000,"score":0,"value":0.0957},{"duration":130000,"score":0,"value":0.0952},{"duration":140000,"score":0,"value":0.0953},{"duration":150000,"score":0,"value":0.0966},{"duration":160000,"score":0,"value":0.0951},{"duration":170000,"score":0,"value":0.0943},{"duration":180000,"score":0,"value":0.0980},{"duration":190000,"score":0,"value":0.0972},{"duration":200000,"score":0,"value":0.0954},{"duration":210000,"score":0,"value":0.0950},{"duration":220000,"score":0,"value":0.0957},{"duration":230000,"score":0,"value":0.0970},{"duration":240000,"score":0,"value":0.0986},{"duration":250000,"score":0,"value":0.0965},{"duration":260000,"score":0,"value":0.0968},{"duration":270000,"score":0,"value":0.0978},{"duration":280000,"score":0,"value":0.0985},{"duration":290000,"score":0,"value":0.0987},{"duration":300000,"score":0,"value":0.0994},{"duration":310000,"score":0,"value":0.0996},{"duration":320000,"score":0,"value":0.0979},{"duration":330000,"score":0,"value":0.0980},{"duration":340000,"score":0,"value":0.1001},{"duration":350000,"score":0,"value":0.1004},{"duration":360000,"score":0,"value":0.1008},{"duration":370000,"score":0,"value":0.1000},{"duration":380000,"score":0,"value":0.0967},{"duration":390000,"score":0,"value":0.0989},{"duration":400000,"score":0,"value":0.0999},{"duration":410000,"score":0,"value":0.0979},{"duration":420000,"score":0,"value":0.0973},{"duration":430000,"score":0,"value":0.0983},{"duration":440000,"score":0,"value":0.0980},{"duration":450000,"score":0,"value":0.0954},{"duration":460000,"score":0,"value":0.0966},{"duration":470000,"score":0,"value":0.0973},{"duration":480000,"score":0,"value":0.0968},{"duration":490000,"score":0,"value":0.0971},{"duration":500000,"score":0,"value":0.0980},{"duration":510000,"score":0,"value":0.0966},{"duration":520000,"score":0,"value":0.0973},{"duration":530000,"score":0,"value":0.0983},{"duration":540000,"score":0,"value":0.0955},{"duration":550000,"score":0,"value":0.0974},{"duration":560000,"score":0,"value":0.0975},{"duration":570000,"score":0,"value":0.0985},{"duration":580000,"score":1,"value":0.0946},{"duration":590000,"score":0,"value":0.0964},{"duration":600000,"score":0,"value":0.0981},{"duration":610000,"score":0,"value":0.0983},{"duration":620000,"score":0,"value":0.1011},{"duration":630000,"score":0,"value":0.1010},{"duration":640000,"score":0,"value":0.0978},{"duration":650000,"score":0,"value":0.0980},{"duration":660000,"score":0,"value":0.0946},{"duration":670000,"score":0,"value":0.0975},{"duration":680000,"score":0,"value":0.0988},{"duration":690000,"score":0,"value":0.0988},{"duration":700000,"score":0,"value":0.1009},{"duration":710000,"score":0,"value":0.0979},{"duration":720000,"score":0,"value":0.0986},{"duration":730000,"score":0,"value":0.1003},{"duration":740000,"score":0,"value":0.1021},{"duration":750000,"score":0,"value":0.0998},{"duration":760000,"score":0,"value":0.0963},{"duration":770000,"score":0,"value":0.1006},{"duration":780000,"score":0,"value":0.1015},{"duration":790000,"score":0,"value":0.0999},{"duration":800000,"score":0,"value":0.1003},{"duration":810000,"score":0,"value":0.0983},{"duration":820000,"score":0,"value":0.0983},{"duration":830000,"score":0,"value":0.0973},{"duration":840000,"score":0,"value":0.0961},{"duration":850000,"score":0,"value":0.0989},{"duration":860000,"score":0,"value":0.0986},{"duration":870000,"score":0,"value":0.1007},{"duration":880000,"score":0,"value":0.0993},{"duration":890000,"score":0,"value":0.1014},{"duration":900000,"score":0,"value":0.0987},{"duration":910000,"score":0,"value":0.1021},{"duration":920000,"score":0,"value":0.0996},{"duration":930000,"score":0,"value":0.0983},{"duration":940000,"score":0,"value":0.0988},{"duration":950000,"score":0,"value":0.1012},{"duration":960000,"score":0,"value":0.1007},{"duration":970000,"score":0,"value":0.1029},{"duration":979999,"score":0,"value":0.0997},{"duration":989999,"score":0,"value":0.1000},{"duration":999999,"score":0,"value":0.1005},{"duration":1009999,"score":0,"value":0.1013},{"duration":1019999,"score":0,"value":0.1038},{"duration":1029999,"score":0,"value":0.1034},{"duration":1039999,"score":0,"value":0.1031},{"duration":1049999,"score":0,"value":0.1039},{"duration":1067559,"score":1,"value":0.0891},{"duration":1077559,"score":1,"value":0.0931},{"duration":1087559,"score":0,"value":0.0986},{"duration":1097559,"score":0,"value":0.0955},{"duration":1107559,"score":0,"value":0.0969},{"duration":1117559,"score":0,"value":0.0970},{"duration":1127559,"score":0,"value":0.0972},{"duration":1137559,"score":0,"value":0.0981},{"duration":1147559,"score":0,"value":0.0998},{"duration":1157559,"score":0,"value":0.0964},{"duration":1167559,"score":0,"value":0.0969},{"duration":1177559,"score":0,"value":0.0971},{"duration":1187559,"score":0,"value":0.0962},{"duration":1197559,"score":0,"value":0.0964},{"duration":1207559,"score":0,"value":0.0960},{"duration":1217559,"score":0,"value":0.0968},{"duration":1227559,"score":0,"value":0.0953},{"duration":1237559,"score":0,"value":0.0958},{"duration":1247559,"score":0,"value":0.0969},{"duration":1257559,"score":0,"value":0.0962},{"duration":1267559,"score":0,"value":0.0973},{"duration":1277559,"score":0,"value":0.0978},{"duration":1287559,"score":0,"value":0.0988},{"duration":1297559,"score":0,"value":0.0988},{"duration":1307559,"score":0,"value":0.1017},{"duration":1317559,"score":0,"value":0.0981},{"duration":1327559,"score":0,"value":0.0972},{"duration":1337559,"score":0,"value":0.0969},{"duration":1347559,"score":0,"value":0.0972},{"duration":1357559,"score":0,"value":0.0979},{"duration":1367559,"score":0,"value":0.1013},{"duration":1377559,"score":0,"value":0.0997},{"duration":1387559,"score":0,"value":0.0950},{"duration":1397559,"score":0,"value":0.0932},{"duration":1407559,"score":0,"value":0.0961},{"duration":1417559,"score":0,"value":0.0951},{"duration":1427559,"score":0,"value":0.0954},{"duration":1437559,"score":0,"value":0.0966},{"duration":1447559,"score":0,"value":0.0954},{"duration":1457559,"score":0,"value":0.0966},{"duration":1467559,"score":0,"value":0.1005},{"duration":1477559,"score":0,"value":0.1000},{"duration":1487559,"score":0,"value":0.0979},{"duration":1497559,"score":0,"value":0.0962},{"duration":1507559,"score":0,"value":0.0990},{"duration":1517559,"score":0,"value":0.0983},{"duration":1527559,"score":0,"value":0.0980},{"duration":1537559,"score":0,"value":0.0976},{"duration":1547559,"score":0,"value":0.1015},{"duration":1557559,"score":0,"value":0.1002},{"duration":1567559,"score":0,"value":0.0978},{"duration":1577559,"score":0,"value":0.0984},{"duration":1587559,"score":0,"value":0.0990},{"duration":1597559,"score":0,"value":0.1004},{"duration":1607559,"score":0,"value":0.0998},{"duration":1617559,"score":0,"value":0.1013},{"duration":1627559,"score":0,"value":0.0973},{"duration":1637559,"score":0,"value":0.0983},{"duration":1647559,"score":0,"value":0.0966},{"duration":1657559,"score":0,"value":0.0967},{"duration":1667559,"score":0,"value":0.0965},{"duration":1677559,"score":0,"value":0.0966},{"duration":1687559,"score":0,"value":0.0953},{"duration":1697559,"score":0,"value":0.0941},{"duration":1707559,"score":0,"value":0.0933},{"duration":1717559,"score":0,"value":0.0934},{"duration":1727559,"score":0,"value":0.0931}],"data_type":"undulation","overall_score":0,"score_ratio":[86.0,13.0,1.0]},{"chart_data":[{"duration":10000,"score":2,"value":134.3168},{"duration":20000,"score":1,"value":163.6262},{"duration":30000,"score":1,"value":169.4083},{"duration":40000,"score":1,"value":174.9730},{"duration":50000,"score":1,"value":172.7893},{"duration":60000,"score":1,"value":179.2929},{"duration":70000,"score":1,"value":180.1197},{"duration":80000,"score":1,"value":179.0555},{"duration":90000,"score":1,"value":178.1161},{"duration":100000,"score":1,"value":177.6688},{"duration":110000,"score":1,"value":177.0247},{"duration":120000,"score":1,"value":176.9115},{"duration":130000,"score":1,"value":178.6713},{"duration":140000,"score":1,"value":179.8781},{"duration":150000,"score":1,"value":177.0325},{"duration":160000,"score":1,"value":178.7695},{"duration":170000,"score":1,"value":178.4138},{"duration":180000,"score":1,"value":178.7123},{"duration":190000,"score":1,"value":178.8016},{"duration":200000,"score":1,"value":176.6654},{"duration":210000,"score":1,"value":177.4454},{"duration":220000,"score":1,"value":177.6691},{"duration":230000,"score":1,"value":178.8493},{"duration":240000,"score":1,"value":181.9439},{"duration":250000,"score":1,"value":181.0500},{"duration":260000,"score":1,"value":180.7184},{"duration":270000,"score":1,"value":179.2538},{"duration":280000,"score":1,"value":180.0144},{"duration":290000,"score":1,"value":179.7712},{"duration":300000,"score":1,"value":179.2772},{"duration":310000,"score":1,"value":175.8432},{"duration":320000,"score":1,"value":176.6129},{"duration":330000,"score":1,"value":175.8808},{"duration":340000,"score":1,"value":180.3112},{"duration":350000,"score":1,"value":180.8213},{"duration":360000,"score":1,"value":183.1084},{"duration":370000,"score":1,"value":181.1371},{"duration":380000,"score":1,"value":181.2516},{"duration":390000,"score":1,"value":182.3576},{"duration":400000,"score":1,"value":176.5486},{"duration":410000,"score":1,"value":178.6766},{"duration":420000,"score":1,"value":179.2926},{"duration":430000,"score":1,"value":176.5506},{"duration":440000,"score":1,"value":177.9447},{"duration":450000,"score":1,"value":176.0013},{"duration":460000,"score":1,"value":179.3669},{"duration":470000,"score":1,"value":181.6134},{"duration":480000,"score":1,"value":179.7204},{"duration":490000,"score":1,"value":179.6391},{"duration":500000,"score":1,"value":180.8548},{"duration":510000,"score":1,"value":177.0033},{"duration":520000,"score":1,"value":178.8542},{"duration":530000,"score":1,"value":178.5725},{"duration":540000,"score":1,"value":176.0974},{"duration":550000,"score":1,"value":176.7425},{"duration":560000,"score":1,"value":178.2522},{"duration":570000,"score":1,"value":180.9520},{"duration":580000,"score":1,"value":175.1452},{"duration":590000,"score":1,"value":178.4444},{"duration":600000,"score":1,"value":178.7218},{"duration":610000,"score":1,"value":177.9271},{"duration":620000,"score":0,"value":185.6004},{"duration":630000,"score":1,"value":184.1520},{"duration":640000,"score":1,"value":179.5981},{"duration":650000,"score":1,"value":177.2984},{"duration":660000,"score":1,"value":181.6227},{"duration":670000,"score":1,"value":178.8347},{"duration":680000,"score":1,"value":179.1706},{"duration":690000,"score":1,"value":179.3664},{"duration":700000,"score":1,"value":183.7808},{"duration":710000,"score":1,"value":181.7694},{"duration":720000,"score":1,"value":179.4585},{"duration":730000,"score":1,"value":180.3997},{"duration":740000,"score":1,"value":178.9849},{"duration":750000,"score":1,"value":181.3632},{"duration":760000,"score":1,"value":166.3547},{"duration":770000,"score":1,"value":177.0423},{"duration":780000,"score":1,"value":181.1260},{"duration":790000,"score":1,"value":181.0701},{"duration":800000,"score":1,"value":177.3314},{"duration":810000,"score":1,"value":176.8085},{"duration":820000,"score":1,"value":174.6115},{"duration":830000,"score":1,"value":179.2311},{"duration":840000,"score":1,"value":178.4962},{"duration":850000,"score":1,"value":178.7637},{"duration":860000,"score":0,"value":185.1964},{"duration":870000,"score":1,"value":177.2273},{"duration":880000,"score":1,"value":178.9175},{"duration":890000,"score":1,"value":181.4282},{"duration":900000,"score":1,"value":183.6736},{"duration":910000,"score":0,"value":186.8457},{"duration":920000,"score":1,"value":176.2040},{"duration":930000,"score":1,"value":175.8750},{"duration":940000,"score":1,"value":178.0422},{"duration":950000,"score":1,"value":177.4103},{"duration":960000,"score":1,"value":179.1636},{"duration":970000,"score":1,"value":178.3443},{"duration":979999,"score":1,"value":180.6726},{"duration":989999,"score":1,"value":177.2129},{"duration":999999,"score":1,"value":178.7919},{"duration":1009999,"score":1,"value":180.5444},{"duration":1019999,"score":1,"value":178.6880},{"duration":1029999,"score":1,"value":183.9324},{"duration":1039999,"score":1,"value":180.9507},{"duration":1049999,"score":1,"value":182.5175},{"duration":1067559,"score":1,"value":162.8310},{"duration":1077559,"score":1,"value":174.3496},{"duration":1087559,"score":1,"value":174.5995},{"duration":1097559,"score":1,"value":174.6401},{"duration":1107559,"score":1,"value":174.2708},{"duration":1117559,"score":1,"value":173.7679},{"duration":1127559,"score":1,"value":174.0903},{"duration":1137559,"score":1,"value":175.0604},{"duration":1147559,"score":1,"value":174.7158},{"duration":1157559,"score":1,"value":174.0250},{"duration":1167559,"score":1,"value":175.7102},{"duration":1177559,"score":1,"value":173.4832},{"duration":1187559,"score":1,"value":174.1802},{"duration":1197559,"score":1,"value":173.1864},{"duration":1207559,"score":1,"value":170.3897},{"duration":1217559,"score":1,"value":176.4003},{"duration":1227559,"score":1,"value":172.8244},{"duration":1237559,"score":1,"value":173.5366},{"duration":1247559,"score":1,"value":174.8400},{"duration":1257559,"score":1,"value":174.4320},{"duration":1267559,"score":1,"value":172.5945},{"duration":1277559,"score":1,"value":173.0124},{"duration":1287559,"score":1,"value":173.7913},{"duration":1297559,"score":1,"value":176.3403},{"duration":1307559,"score":1,"value":178.8024},{"duration":1317559,"score":1,"value":175.2889},{"duration":1327559,"score":1,"value":175.1972},{"duration":1337559,"score":1,"value":173.0522},{"duration":1347559,"score":1,"value":173.8559},{"duration":1357559,"score":1,"value":173.3947},{"duration":1367559,"score":1,"value":179.1846},{"duration":1377559,"score":1,"value":181.3846},{"duration":1387559,"score":1,"value":172.8163},{"duration":1397559,"score":1,"value":171.9958},{"duration":1407559,"score":1,"value":180.8694},{"duration":1417559,"score":1,"value":171.9220},{"duration":1427559,"score":1,"value":173.1664},{"duration":1437559,"score":1,"value":175.2102},{"duration":1447559,"score":1,"value":178.4058},{"duration":1457559,"score":1,"value":177.7647},{"duration":1467559,"score":1,"value":175.9033},{"duration":1477559,"score":1,"value":175.1784},{"duration":1487559,"score":1,"value":174.4841},{"duration":1497559,"score":1,"value":172.9662},{"duration":1507559,"score":1,"value":178.8860},{"duration":1517559,"score":1,"value":174.5085},{"duration":1527559,"score":1,"value":174.2861},{"duration":1537559,"score":1,"value":175.3884},{"duration":1547559,"score":1,"value":177.6133},{"duration":1557559,"score":1,"value":173.7768},{"duration":1567559,"score":1,"value":171.4788},{"duration":1577559,"score":1,"value":171.9617},{"duration":1587559,"score":1,"value":178.1130},{"duration":1597559,"score":1,"value":178.0249},{"duration":1607559,"score":1,"value":175.4490},{"duration":1617559,"score":1,"value":178.7035},{"duration":1627559,"score":1,"value":165.6604},{"duration":1637559,"score":1,"value":170.5242},{"duration":1647559,"score":1,"value":173.7757},{"duration":1657559,"score":1,"value":170.7367},{"duration":1667559,"score":1,"value":171.6575},{"duration":1677559,"score":1,"value":172.3306},{"duration":1687559,"score":1,"value":170.7578},{"duration":1697559,"score":1,"value":165.7122},{"duration":1707559,"score":1,"value":167.0310},{"duration":1717559,"score":1,"value":168.4177},{"duration":1727559,"score":1,"value":167.2800}],"data_type":"effective_contact_time","overall_score":1,"score_ratio":[16.0,82.0,2.0]},{"chart_data":[{"duration":10000,"score":0,"value":165.2397},{"duration":20000,"score":1,"value":192.8432},{"duration":30000,"score":1,"value":199.1016},{"duration":40000,"score":1,"value":199.2456},{"duration":50000,"score":1,"value":197.5133},{"duration":60000,"score":1,"value":195.8755},{"duration":70000,"score":1,"value":200.7742},{"duration":80000,"score":1,"value":197.2238},{"duration":90000,"score":1,"value":197.8330},{"duration":100000,"score":1,"value":196.0641},{"duration":110000,"score":1,"value":195.2155},{"duration":120000,"score":1,"value":198.0025},{"duration":130000,"score":1,"value":196.6466},{"duration":140000,"score":1,"value":196.2553},{"duration":150000,"score":1,"value":199.0870},{"duration":160000,"score":1,"value":196.3865},{"duration":170000,"score":1,"value":195.4482},{"duration":180000,"score":1,"value":200.3505},{"duration":190000,"score":1,"value":199.2785},{"duration":200000,"score":1,"value":197.6230},{"duration":210000,"score":1,"value":196.8275},{"duration":220000,"score":1,"value":197.5790},{"duration":230000,"score":1,"value":198.9684},{"duration":240000,"score":1,"value":200.0013},{"duration":250000,"score":1,"value":197.4856},{"duration":260000,"score":1,"value":198.0800},{"duration":270000,"score":1,"value":200.0176},{"duration":280000,"score":1,"value":200.5277},{"duration":290000,"score":1,"value":200.8123},{"duration":300000,"score":1,"value":201.9140},{"duration":310000,"score":1,"value":203.5304},{"duration":320000,"score":1,"value":200.9593},{"duration":330000,"score":1,"value":201.4591},{"duration":340000,"score":1,"value":202.7379},{"duration":350000,"score":1,"value":202.8664},{"duration":360000,"score":1,"value":202.5166},{"duration":370000,"score":1,"value":202.3288},{"duration":380000,"score":1,"value":197.6954},{"duration":390000,"score":1,"value":200.1911},{"duration":400000,"score":2,"value":203.7985},{"duration":410000,"score":1,"value":200.4109},{"duration":420000,"score":1,"value":199.3434},{"duration":430000,"score":1,"value":201.4865},{"duration":440000,"score":1,"value":200.6279},{"duration":450000,"score":1,"value":197.9339},{"duration":460000,"score":1,"value":198.0811},{"duration":470000,"score":1,"value":198.4525},{"duration":480000,"score":1,"value":198.5593},{"duration":490000,"score":1,"value":198.7029},{"duration":500000,"score":1,"value":199.5850},{"duration":510000,"score":1,"value":199.2182},{"duration":520000,"score":1,"value":199.4200},{"duration":530000,"score":1,"value":200.8845},{"duration":540000,"score":1,"value":197.9773},{"duration":550000,"score":1,"value":200.3659},{"duration":560000,"score":1,"value":200.0440},{"duration":570000,"score":1,"value":200.2602},{"duration":580000,"score":1,"value":195.8732},{"duration":590000,"score":1,"value":198.1187},{"duration":600000,"score":1,"value":200.5606},{"duration":610000,"score":1,"value":201.1334},{"duration":620000,"score":1,"value":202.1784},{"duration":630000,"score":1,"value":202.5944},{"duration":640000,"score":1,"value":199.9598},{"duration":650000,"score":1,"value":201.0876},{"duration":660000,"score":1,"value":194.4390},{"duration":670000,"score":1,"value":199.7678},{"duration":680000,"score":1,"value":201.4291},{"duration":690000,"score":1,"value":201.2764},{"duration":700000,"score":1,"value":202.6512},{"duration":710000,"score":1,"value":199.2813},{"duration":720000,"score":1,"value":201.0898},{"duration":730000,"score":1,"value":203.1277},{"duration":740000,"score":2,"value":205.8578},{"duration":750000,"score":1,"value":202.0481},{"duration":760000,"score":1,"value":202.5087},{"duration":770000,"score":2,"value":204.6292},{"duration":780000,"score":2,"value":204.2916},{"duration":790000,"score":1,"value":202.1171},{"duration":800000,"score":2,"value":204.0555},{"duration":810000,"score":1,"value":201.5051},{"duration":820000,"score":1,"value":202.3294},{"duration":830000,"score":1,"value":199.3726},{"duration":840000,"score":1,"value":198.0320},{"duration":850000,"score":1,"value":201.8419},{"duration":860000,"score":1,"value":199.0014},{"duration":870000,"score":2,"value":204.8037},{"duration":880000,"score":1,"value":202.1428},{"duration":890000,"score":1,"value":204.0680},{"duration":900000,"score":1,"value":199.6325},{"duration":910000,"score":1,"value":202.9995},{"duration":920000,"score":2,"value":203.6329},{"duration":930000,"score":1,"value":201.9493},{"duration":940000,"score":1,"value":201.8651},{"duration":950000,"score":2,"value":205.3025},{"duration":960000,"score":2,"value":204.0489},{"duration":970000,"score":2,"value":207.2179},{"duration":979999,"score":1,"value":201.9239},{"duration":989999,"score":2,"value":203.8069},{"duration":999999,"score":1,"value":203.8416},{"duration":1009999,"score":2,"value":204.3441},{"duration":1019999,"score":2,"value":208.3316},{"duration":1029999,"score":2,"value":205.9299},{"duration":1039999,"score":2,"value":206.5896},{"duration":1049999,"score":2,"value":206.9973},{"duration":1067559,"score":2,"value":209.6051},{"duration":1077559,"score":1,"value":198.2455},{"duration":1087559,"score":1,"value":203.3603},{"duration":1097559,"score":1,"value":198.6835},{"duration":1107559,"score":1,"value":200.7784},{"duration":1117559,"score":1,"value":200.8558},{"duration":1127559,"score":1,"value":201.0604},{"duration":1137559,"score":1,"value":202.0011},{"duration":1147559,"score":2,"value":204.5298},{"duration":1157559,"score":1,"value":200.1495},{"duration":1167559,"score":1,"value":200.1414},{"duration":1177559,"score":1,"value":201.2959},{"duration":1187559,"score":1,"value":199.8217},{"duration":1197559,"score":1,"value":200.4571},{"duration":1207559,"score":1,"value":200.7844},{"duration":1217559,"score":1,"value":199.7370},{"duration":1227559,"score":1,"value":199.0628},{"duration":1237559,"score":1,"value":199.4112},{"duration":1247559,"score":1,"value":200.3656},{"duration":1257559,"score":1,"value":199.6473},{"duration":1267559,"score":1,"value":201.8226},{"duration":1277559,"score":1,"value":202.2595},{"duration":1287559,"score":2,"value":203.3971},{"duration":1297559,"score":1,"value":202.5383},{"duration":1307559,"score":2,"value":205.3688},{"duration":1317559,"score":1,"value":201.8752},{"duration":1327559,"score":1,"value":200.7294},{"duration":1337559,"score":1,"value":201.1404},{"duration":1347559,"score":1,"value":201.2020},{"duration":1357559,"score":1,"value":202.2832},{"duration":1367559,"score":2,"value":204.7461},{"duration":1377559,"score":1,"value":201.8211},{"duration":1387559,"score":1,"value":198.5179},{"duration":1397559,"score":1,"value":196.4512},{"duration":1407559,"score":1,"value":196.9917},{"duration":1417559,"score":1,"value":199.1031},{"duration":1427559,"score":1,"value":199.0253},{"duration":1437559,"score":1,"value":199.9534},{"duration":1447559,"score":1,"value":197.0890},{"duration":1457559,"score":1,"value":199.0212},{"duration":1467559,"score":2,"value":205.0618},{"duration":1477559,"score":2,"value":204.5399},{"duration":1487559,"score":1,"value":201.9224},{"duration":1497559,"score":1,"value":200.1614},{"duration":1507559,"score":1,"value":201.8343},{"duration":1517559,"score":1,"value":202.3825},{"duration":1527559,"score":1,"value":202.1729},{"duration":1537559,"score":1,"value":201.1597},{"duration":1547559,"score":2,"value":205.6640},{"duration":1557559,"score":2,"value":205.3445},{"duration":1567559,"score":1,"value":202.9559},{"duration":1577559,"score":2,"value":203.6623},{"duration":1587559,"score":1,"value":202.1079},{"duration":1597559,"score":2,"value":203.9746},{"duration":1607559,"score":2,"value":204.1362},{"duration":1617559,"score":2,"value":204.9743},{"duration":1627559,"score":2,"value":204.4734},{"duration":1637559,"score":2,"value":204.0955},{"duration":1647559,"score":1,"value":200.3438},{"duration":1657559,"score":1,"value":201.6677},{"duration":1667559,"score":1,"value":201.1806},{"duration":1677559,"score":1,"value":200.9573},{"duration":1687559,"score":1,"value":199.7475},{"duration":1697559,"score":1,"value":199.8598},{"duration":1707559,"score":1,"value":198.3862},{"duration":1717559,"score":1,"value":197.9840},{"duration":1727559,"score":1,"value":197.9525}],"data_type":"effective_flight_time","overall_score":1,"score_ratio":[1.0,68.0,31.0]}],"sampling_rate":10000,"service_name":"Myotest","version":2}]}