[{"heart_rate":76.0,"heart_rate_max":77.0,"heart_rate_min":75.0,"start_time":1612947900000,"end_time":1612947959000},{"heart_rate":85.0,"heart_rate_max":92.0,"heart_rate_min":77.0,"start_time":1612947960000,"end_time":1612948019000},{"heart_rate":86.0,"heart_rate_max":90.0,"heart_rate_min":83.0,"start_time":1612948020000,"end_time":1612948079000},{"heart_rate":93.0,"heart_rate_max":95.0,"heart_rate_min":92.0,"start_time":1612948080000,"end_time":1612948139000},{"heart_rate":80.0,"heart_rate_max":95.0,"heart_rate_min":77.0,"start_time":1612948380000,"end_time":1612948439000},{"heart_rate":81.0,"heart_rate_max":85.0,"heart_rate_min":78.0,"start_time":1612948440000,"end_time":1612948499000},{"heart_rate":83.0,"heart_rate_max":96.0,"heart_rate_min":74.0,"start_time":1612948500000,"end_time":1612948559000},{"heart_rate":85.0,"heart_rate_max":100.0,"heart_rate_min":78.0,"start_time":1612948560000,"end_time":1612948619000},{"heart_rate":76.0,"heart_rate_max":83.0,"heart_rate_min":74.0,"start_time":1612948620000,"end_time":1612948679000},{"heart_rate":79.0,"heart_rate_max":83.0,"heart_rate_min":76.0,"start_time":1612948680000,"end_time":1612948739000},{"heart_rate":84.0,"heart_rate_max":87.0,"heart_rate_min":81.0,"start_time":1612948740000,"end_time":1612948799000},{"heart_rate":83.0,"heart_rate_max":86.0,"heart_rate_min":82.0,"start_time":1612948800000,"end_time":1612948859000},{"heart_rate":83.0,"heart_rate_max":88.0,"heart_rate_min":75.0,"start_time":1612948860000,"end_time":1612948919000},{"heart_rate":74.0,"heart_rate_max":81.0,"heart_rate_min":67.0,"start_time":1612948920000,"end_time":1612948979000},{"heart_rate":75.0,"heart_rate_max":79.0,"heart_rate_min":66.0,"start_time":1612948980000,"end_time":1612949039000},{"heart_rate":77.0,"heart_rate_max":79.0,"heart_rate_min":76.0,"start_time":1612949040000,"end_time":1612949099000},{"heart_rate":102.0,"heart_rate_max":102.0,"heart_rate_min":102.0,"start_time":1612949100000,"end_time":1612949159000},{"heart_rate":83.0,"heart_rate_max":84.0,"heart_rate_min":83.0,"start_time":1612949160000,"end_time":1612949219000},{"heart_rate":91.0,"heart_rate_max":93.0,"heart_rate_min":91.0,"start_time":1612949280000,"end_time":1612949339000},{"heart_rate":92.0,"heart_rate_max":97.0,"heart_rate_min":89.0,"start_time":1612949340000,"end_time":1612949399000},{"heart_rate":96.0,"heart_rate_max":96.0,"heart_rate_min":96.0,"start_time":1612949400000,"end_time":1612949459000},{"heart_rate":95.0,"heart_rate_max":99.0,"heart_rate_min":94.0,"start_time":1612949460000,"end_time":1612949519000},{"heart_rate":85.0,"heart_rate_max":89.0,"heart_rate_min":83.0,"start_time":1612949580000,"end_time":1612949639000},{"heart_rate":93.0,"heart_rate_max":93.0,"heart_rate_min":93.0,"start_time":1612949640000,"end_time":1612949699000},{"heart_rate":71.0,"heart_rate_max":77.0,"heart_rate_min":67.0,"start_time":1612949880000,"end_time":1612949939000},{"heart_rate":79.0,"heart_rate_max":85.0,"heart_rate_min":75.0,"start_time":1612949940000,"end_time":1612949999000},{"heart_rate":76.0,"heart_rate_max":82.0,"heart_rate_min":71.0,"start_time":1612950000000,"end_time":1612950059000},{"heart_rate":78.0,"heart_rate_max":84.0,"heart_rate_min":72.0,"start_time":1612950060000,"end_time":1612950119000},{"heart_rate":73.0,"heart_rate_max":82.0,"heart_rate_min":69.0,"start_time":1612950120000,"end_time":1612950179000},{"heart_rate":72.0,"heart_rate_max":80.0,"heart_rate_min":68.0,"start_time":1612950180000,"end_time":1612950239000},{"heart_rate":78.0,"heart_rate_max":79.0,"heart_rate_min":78.0,"start_time":1612950240000,"end_time":1612950299000},{"heart_rate":76.0,"heart_rate_max":83.0,"heart_rate_min":73.0,"start_time":1612950300000,"end_time":1612950359000},{"heart_rate":86.0,"heart_rate_max":88.0,"heart_rate_min":84.0,"start_time":1612950360000,"end_time":1612950419000},{"heart_rate":83.0,"heart_rate_max":88.0,"heart_rate_min":78.0,"start_time":1612950420000,"end_time":1612950479000},{"heart_rate":82.0,"heart_rate_max":85.0,"heart_rate_min":80.0,"start_time":1612950480000,"end_time":1612950539000},{"heart_rate":75.0,"heart_rate_max":80.0,"heart_rate_min":72.0,"start_time":1612950540000,"end_time":1612950599000},{"heart_rate":76.0,"heart_rate_max":92.0,"heart_rate_min":65.0,"start_time":1612950600000,"end_time":1612950659000},{"heart_rate":74.0,"heart_rate_max":83.0,"heart_rate_min":66.0,"start_time":1612950780000,"end_time":1612950839000},{"heart_rate":66.0,"heart_rate_max":74.0,"heart_rate_min":62.0,"start_time":1612950840000,"end_time":1612950899000},{"heart_rate":74.0,"heart_rate_max":81.0,"heart_rate_min":72.0,"start_time":1612950900000,"end_time":1612950959000},{"heart_rate":76.0,"heart_rate_max":80.0,"heart_rate_min":73.0,"start_time":1612950960000,"end_time":1612951019000},{"heart_rate":73.0,"heart_rate_max":76.0,"heart_rate_min":71.0,"start_time":1612951020000,"end_time":1612951079000},{"heart_rate":75.0,"heart_rate_max":80.0,"heart_rate_min":69.0,"start_time":1612951080000,"end_time":1612951139000},{"heart_rate":76.0,"heart_rate_max":79.0,"heart_rate_min":72.0,"start_time":1612951140000,"end_time":1612951199000}]