[{"score":98,"score_max":99,"score_min":96,"flag":1,"level":1,"start_time":1609714860000,"end_time":1609714919999},{"score":59,"score_max":95,"score_min":29,"flag":1,"level":0,"start_time":1609714920000,"end_time":1609714979999},{"score":61,"score_max":78,"score_min":34,"flag":1,"level":0,"start_time":1609714980000,"end_time":1609715039999},{"score":10,"score_max":29,"score_min":4,"flag":1,"level":0,"start_time":1609715040000,"end_time":1609715099999},{"score":65,"score_max":99,"score_min":13,"flag":1,"level":1,"start_time":1609715100000,"end_time":1609715159999},{"score":99,"score_max":100,"score_min":99,"flag":1,"level":1,"start_time":1609715160000,"end_time":1609715219999},{"score":8,"score_max":15,"score_min":4,"flag":1,"level":0,"start_time":1609715340000,"end_time":1609715399999},{"score":22,"score_max":51,"score_min":14,"flag":1,"level":0,"start_time":1609715400000,"end_time":1609715459999},{"score":34,"score_max":60,"score_min":5,"flag":1,"level":0,"start_time":1609715460000,"end_time":1609715519999},{"score":2,"score_max":5,"score_min":1,"flag":1,"level":0,"start_time":1609715520000,"end_time":1609715579999},{"score":2,"score_max":3,"score_min":2,"flag":1,"level":0,"start_time":1609715580000,"end_time":1609715639999},{"score":4,"score_max":18,"score_min":1,"flag":1,"level":0,"start_time":1609715640000,"end_time":1609715699999},{"score":11,"score_max":19,"score_min":2,"flag":1,"level":0,"start_time":1609715700000,"end_time":1609715759999},{"score":0,"score_max":2,"score_min":0,"flag":1,"level":0,"start_time":1609715760000,"end_time":1609715819999},{"score":0,"score_max":1,"score_min":0,"flag":1,"level":0,"start_time":1609715820000,"end_time":1609715879999},{"score":2,"score_max":4,"score_min":1,"flag":1,"level":0,"start_time":1609715880000,"end_time":1609715939999},{"score":1,"score_max":4,"score_min":1,"flag":1,"level":0,"start_time":1609715940000,"end_time":1609715999999},{"score":19,"score_max":33,"score_min":2,"flag":1,"level":0,"start_time":1609716000000,"end_time":1609716059999},{"score":5,"score_max":22,"score_min":3,"flag":1,"level":0,"start_time":1609716060000,"end_time":1609716119999},{"score":40,"score_max":71,"score_min":2,"flag":1,"level":0,"start_time":1609716120000,"end_time":1609716179999},{"score":17,"score_max":66,"score_min":1,"flag":1,"level":0,"start_time":1609716180000,"end_time":1609716239999},{"score":0,"score_max":1,"score_min":0,"flag":1,"level":0,"start_time":1609716240000,"end_time":1609716299999},{"score":11,"score_max":60,"score_min":0,"flag":1,"level":0,"start_time":1609716300000,"end_time":1609716359999},{"score":26,"score_max":66,"score_min":0,"flag":1,"level":0,"start_time":1609716360000,"end_time":1609716419999},{"score":0,"score_max":0,"score_min":0,"flag":1,"level":0,"start_time":1609716420000,"end_time":1609716479999},{"score":0,"score_max":0,"score_min":0,"flag":1,"level":0,"start_time":1609716480000,"end_time":1609716539999},{"score":0,"score_max":1,"score_min":0,"flag":1,"level":0,"start_time":1609716540000,"end_time":1609716599999},{"score":8,"score_max":11,"score_min":4,"flag":1,"level":0,"start_time":1609716600000,"end_time":1609716659999},{"score":0,"score_max":4,"score_min":0,"flag":1,"level":0,"start_time":1609716660000,"end_time":1609716719999},{"score":0,"score_max":0,"score_min":0,"flag":1,"level":0,"start_time":1609716720000,"end_time":1609716779999},{"score":0,"score_max":1,"score_min":0,"flag":1,"level":0,"start_time":1609716780000,"end_time":1609716839999},{"score":0,"score_max":2,"score_min":0,"flag":1,"level":0,"start_time":1609716840000,"end_time":1609716899999},{"score":7,"score_max":59,"score_min":0,"flag":1,"level":0,"start_time":1609716900000,"end_time":1609716959999},{"score":82,"score_max":92,"score_min":62,"flag":1,"level":1,"start_time":1609716960000,"end_time":1609717019999},{"score":78,"score_max":91,"score_min":66,"flag":1,"level":1,"start_time":1609717020000,"end_time":1609717079999},{"score":90,"score_max":99,"score_min":71,"flag":1,"level":1,"start_time":1609717080000,"end_time":1609717139999},{"score":98,"score_max":99,"score_min":98,"flag":1,"level":1,"start_time":1609717140000,"end_time":1609717199999},{"score":72,"score_max":100,"score_min":3,"flag":1,"level":1,"start_time":1609717200000,"end_time":1609717259999},{"score":14,"score_max":52,"score_min":0,"flag":1,"level":0,"start_time":1609717260000,"end_time":1609717319999},{"score":74,"score_max":100,"score_min":53,"flag":1,"level":0,"start_time":1609717320000,"end_time":1609717379999},{"score":95,"score_max":100,"score_min":59,"flag":1,"level":1,"start_time":1609717380000,"end_time":1609717439999},{"score":8,"score_max":9,"score_min":8,"flag":1,"level":0,"start_time":1609717440000,"end_time":1609717499999},{"score":50,"score_max":98,"score_min":9,"flag":1,"level":0,"start_time":1609717500000,"end_time":1609717559999},{"score":94,"score_max":98,"score_min":89,"flag":1,"level":1,"start_time":1609717560000,"end_time":1609717619999},{"score":98,"score_max":100,"score_min":98,"flag":1,"level":1,"start_time":1609717620000,"end_time":1609717679999},{"score":0,"score_max":0,"score_min":0,"flag":1,"level":0,"start_time":1609717860000,"end_time":1609717919999},{"score":0,"score_max":0,"score_min":0,"flag":1,"level":0,"start_time":1609717920000,"end_time":1609717979999},{"score":0,"score_max":1,"score_min":0,"flag":1,"level":0,"start_time":1609717980000,"end_time":1609718039999},{"score":0,"score_max":0,"score_min":0,"flag":1,"level":0,"start_time":1609718040000,"end_time":1609718099999},{"score":40,"score_max":46,"score_min":26,"flag":1,"level":0,"start_time":1609718100000,"end_time":1609718159999},{"score":17,"score_max":43,"score_min":1,"flag":1,"level":0,"start_time":1609718160000,"end_time":1609718219999},{"score":1,"score_max":4,"score_min":1,"flag":1,"level":0,"start_time":1609718220000,"end_time":1609718279999},{"score":56,"score_max":100,"score_min":5,"flag":1,"level":0,"start_time":1609718280000,"end_time":1609718339999}]